Workbook
Name LenderList: 'Loan Terms'!$A$4:$A$16
Name LoanTermsTable: 'Loan Terms'!$A$4:$M$16
Name SOFR_30D: 'Treasury Yields'!$G$8
Name UST_10Y: 'Treasury Yields'!$G$6
Name UST_30Y: 'Treasury Yields'!$G$7
Name UST_5Y: 'Treasury Yields'!$G$4
Name UST_7Y: 'Treasury Yields'!$G$5

Sheet Loan Assumptions
B2: LOAN ASSUMPTIONS — NEW DEBT (FREE & CLEAR)
B3: Select a loan program from the dropdown (yellow cell). All terms populate automatically.
B5: Loan Program | C5: Fannie Mae — Conventional
B7: LTV | C7: =INDEX('Loan Terms'!$F$4:$F$16,MATCH($C$5,'Loan Terms'!$A$4:$A$16,0)) -> 0.75
B8: Interest Rate | C8: =INDEX('Loan Terms'!$E$4:$E$16,MATCH($C$5,'Loan Terms'!$A$4:$A$16,0)) -> 0.0618
B9: DSCR Requirement (reference) | C9: =INDEX('Loan Terms'!$G$4:$G$16,MATCH($C$5,'Loan Terms'!$A$4:$A$16,0)) -> 1.25
B10: Interest Only (Years) | C10: =INDEX('Loan Terms'!$H$4:$H$16,MATCH($C$5,'Loan Terms'!$A$4:$A$16,0)) -> 3
B11: Loan Term (Months) | C11: =INDEX('Loan Terms'!$I$4:$I$16,MATCH($C$5,'Loan Terms'!$A$4:$A$16,0)) -> 120
B12: Amortization (Months) | C12: =IF(INDEX('Loan Terms'!$J$4:$J$16,MATCH($C$5,'Loan Terms'!$A$4:$A$16,0))=0,"Interest Only",INDEX('Loan Terms'!$J$4:$J$16,MATCH($C$5,'Loan Terms'!$A$4:$A$16,0))) -> 360
B15: Pricing Detail
B16: Index | C16: =INDEX('Loan Terms'!$B$4:$B$16,MATCH($C$5,'Loan Terms'!$A$4:$A$16,0)) -> UST 10 Yr
B17: Index Rate (live) | C17: =INDEX('Loan Terms'!$C$4:$C$16,MATCH($C$5,'Loan Terms'!$A$4:$A$16,0)) -> 0.0463
B18: Spread (bps) | C18: =INDEX('Loan Terms'!$D$4:$D$16,MATCH($C$5,'Loan Terms'!$A$4:$A$16,0)) -> 155
B19: Rate Type | C19: =INDEX('Loan Terms'!$K$4:$K$16,MATCH($C$5,'Loan Terms'!$A$4:$A$16,0)) -> Fixed
B20: Recourse | C20: =INDEX('Loan Terms'!$L$4:$L$16,MATCH($C$5,'Loan Terms'!$A$4:$A$16,0)) -> Non-Recourse
B21: Notes | C21: =INDEX('Loan Terms'!$M$4:$M$16,MATCH($C$5,'Loan Terms'!$A$4:$A$16,0)) -> DUS program; 80% max LTV in some markets; tiered pricing (Tier 2 shown). Green/affordable discounts available.
B23: Estimates only — not a quote. Verify spreads with lenders before underwriting.

Sheet Loan Terms
A1: ESTIMATED LOAN TERMS — MULTIFAMILY DEBT (LOOKUP TABLE)
A2: Blue cells = editable placeholder assumptions (spreads & terms — update to current market quotes). Interest Rate = Index Rate (live) + Spread. Amortization of 0 = full-term Interest Only.
A3: Loan Program | B3: Index | C3: Index Rate | D3: Spread (bps) | E3: Interest Rate | F3: Max LTV | G3: Min DSCR | H3: Interest Only (Yrs) | I3: Loan Term (Months) | J3: Amortization (Months) | K3: Rate Type | L3: Recourse | M3: Notes
A4: Fannie Mae — Conventional | B4: UST 10 Yr | C4: =INDEX('Treasury Yields'!$G$4:$G$9,MATCH(B4,'Treasury Yields'!$A$4:$A$9,0)) -> 0.0463 | D4: 155 | E4: =C4+D4/10000 -> 0.0618 | F4: 0.75 | G4: 1.25 | H4: 3 | I4: 120 | J4: 360 | K4: Fixed | L4: Non-Recourse | M4: DUS program; 80% max LTV in some markets; tiered pricing (Tier 2 shown). Green/affordable discounts available.
A5: Freddie Mac — Conventional | B5: UST 10 Yr | C5: =INDEX('Treasury Yields'!$G$4:$G$9,MATCH(B5,'Treasury Yields'!$A$4:$A$9,0)) -> 0.0463 | D5: 150 | E5: =C5+D5/10000 -> 0.0613 | F5: 0.75 | G5: 1.25 | H5: 3 | I5: 120 | J5: 360 | K5: Fixed | L5: Non-Recourse | M5: Optigo conventional; index-lock & early rate-lock available; pricing varies by market/leverage tier.
A6: Fannie Mae — Small Balance | B6: UST 10 Yr | C6: =INDEX('Treasury Yields'!$G$4:$G$9,MATCH(B6,'Treasury Yields'!$A$4:$A$9,0)) -> 0.0463 | D6: 205 | E6: =C6+D6/10000 -> 0.0668 | F6: 0.8 | G6: 1.25 | H6: 1 | I6: 120 | J6: 360 | K6: Fixed | L6: Non-Recourse | M6: Small Loan program (typically ≤$9MM); streamlined docs; step-down prepay available.
A7: Freddie Mac — SBL | B7: UST 10 Yr | C7: =INDEX('Treasury Yields'!$G$4:$G$9,MATCH(B7,'Treasury Yields'!$A$4:$A$9,0)) -> 0.0463 | D7: 200 | E7: =C7+D7/10000 -> 0.0663 | F7: 0.8 | G7: 1.25 | H7: 1 | I7: 120 | J7: 360 | K7: Fixed | L7: Non-Recourse | M7: SBL $1–$7.5MM; hybrid ARM options; LTV/DSCR vary by market tier (Top/Standard/Small/Very Small).
A8: HUD/FHA — 223(f) | B8: UST 10 Yr | C8: =INDEX('Treasury Yields'!$G$4:$G$9,MATCH(B8,'Treasury Yields'!$A$4:$A$9,0)) -> 0.0463 | D8: 110 | E8: =C8+D8/10000 -> 0.0573 | F8: 0.85 | G8: 1.176 | H8: 0 | I8: 420 | J8: 420 | K8: Fixed | L8: Non-Recourse | M8: 35-yr fully amortizing; add ~0.60% annual MIP (0.25% green) on top of note rate; 3–5 mo processing.
A9: HUD/FHA — 221(d)(4) | B9: UST 10 Yr | C9: =INDEX('Treasury Yields'!$G$4:$G$9,MATCH(B9,'Treasury Yields'!$A$4:$A$9,0)) -> 0.0463 | D9: 140 | E9: =C9+D9/10000 -> 0.0603 | F9: 0.85 | G9: 1.176 | H9: 0 | I9: 480 | J9: 480 | K9: Fixed | L9: Non-Recourse | M9: New construction/sub rehab; 40-yr am after ~3-yr IO construction period; add ~0.65% MIP; long processing.
A10: Life Company (LifeCo) | B10: UST 10 Yr | C10: =INDEX('Treasury Yields'!$G$4:$G$9,MATCH(B10,'Treasury Yields'!$A$4:$A$9,0)) -> 0.0463 | D10: 135 | E10: =C10+D10/10000 -> 0.0598 | F10: 0.65 | G10: 1.35 | H10: 2 | I10: 120 | J10: 360 | K10: Fixed | L10: Non-Recourse | M10: Best pricing at ≤65% LTV on stabilized Class A/B; forward commitments available; yield maintenance.
A11: CMBS / Conduit | B11: UST 10 Yr | C11: =INDEX('Treasury Yields'!$G$4:$G$9,MATCH(B11,'Treasury Yields'!$A$4:$A$9,0)) -> 0.0463 | D11: 250 | E11: =C11+D11/10000 -> 0.0713 | F11: 0.75 | G11: 1.25 | H11: 5 | I11: 120 | J11: 360 | K11: Fixed | L11: Non-Recourse | M11: Full-term IO common at ≤65% LTV; defeasance prepay; cash management triggers.
A12: Bank — Balance Sheet | B12: UST 5 Yr | C12: =INDEX('Treasury Yields'!$G$4:$G$9,MATCH(B12,'Treasury Yields'!$A$4:$A$9,0)) -> 0.0433 | D12: 225 | E12: =C12+D12/10000 -> 0.0658 | F12: 0.7 | G12: 1.25 | H12: 1 | I12: 60 | J12: 300 | K12: Fixed | L12: Recourse | M12: 5-yr fixed / 25-yr am typical; recourse often burns off at DSCR test; deposits may improve pricing.
A13: Credit Union | B13: UST 5 Yr | C13: =INDEX('Treasury Yields'!$G$4:$G$9,MATCH(B13,'Treasury Yields'!$A$4:$A$9,0)) -> 0.0433 | D13: 235 | E13: =C13+D13/10000 -> 0.0668 | F13: 0.75 | G13: 1.25 | H13: 0 | I13: 60 | J13: 360 | K13: Fixed | L13: Recourse (varies) | M13: Often no prepayment penalty; membership required; slower execution on larger deals.
A14: Bridge — Debt Fund | B14: 30-Day Avg SOFR | C14: =INDEX('Treasury Yields'!$G$4:$G$9,MATCH(B14,'Treasury Yields'!$A$4:$A$9,0)) -> 0.0362 | D14: 300 | E14: =C14+D14/10000 -> 0.0662 | F14: 0.7 | G14: 1 | H14: 3 | I14: 36 | J14: 0 | K14: Floating | L14: Non-Recourse (carve-outs) | M14: Typically SOFR + 275–400 floating, full-term IO; 70–80% LTC; 1+1 extensions; rate cap required.
A15: Bridge — Bank | B15: 30-Day Avg SOFR | C15: =INDEX('Treasury Yields'!$G$4:$G$9,MATCH(B15,'Treasury Yields'!$A$4:$A$9,0)) -> 0.0362 | D15: 250 | E15: =C15+D15/10000 -> 0.0612 | F15: 0.65 | G15: 1.05 | H15: 2 | I15: 24 | J15: 0 | K15: Floating | L15: Recourse (partial) | M15: Cheaper than debt-fund bridge but lower leverage and partial recourse; renovation/lease-up deals.
A16: Mezzanine / Pref Equity | B16: Fixed (no index) | C16: =INDEX('Treasury Yields'!$G$4:$G$9,MATCH(B16,'Treasury Yields'!$A$4:$A$9,0)) -> 0 | D16: 1250 | E16: =C16+D16/10000 -> 0.125 | F16: 0.85 | G16: 1.05 | H16: 10 | I16: 120 | J16: 0 | K16: Fixed | L16: Non-Recourse | M16: Placeholder 12.5% current pay+accrual; sized to ~85% combined LTV / 1.05x combined DSCR behind senior.
A18: All spreads and terms are PLACEHOLDER market estimates as of Aug 2026 — edit the blue cells to match live lender quotes. Agency/HUD/LifeCo/CMBS price over the 10-Yr UST; banks & credit unions over the 5-Yr UST; bridge over 30-Day Avg SOFR. Actual pricing varies with leverage, market, sponsorship, and deal size. Estimates only — not a loan quote or commitment.

Sheet Treasury Yields
A1: LIVE INDEX RATES — U.S. TREASURY & SOFR
A2: Live pull via =WEBSERVICE() from FRED (St. Louis Fed). Requires Excel for Windows + internet. If the pull fails, the yellow Manual Override column is used automatically. Press Ctrl+Alt+F9 to refresh.
A3: Index | B3: FRED Series | C3: Request URL (auto-built) | D3: Raw CSV Response | E3: Parsed Live Rate | F3: Manual Override | G3: RATE USED | H3: Override As-Of
A4: UST 5 Yr | B4: DGS5 | C4: ="https://fred.stlouisfed.org/graph/fredgraph.csv?id="&B4&"&cosd="&TEXT(TODAY()-21,"YYYY-MM-DD") -> https://fred.stlouisfed.org/graph/fredgraph.csv?id=DGS5&cosd=2026-07-15 | D4: =IFERROR(_xludf.webservice(C4),"") | E4: =IFERROR(VALUE(TRIM(RIGHT(SUBSTITUTE(SUBSTITUTE(SUBSTITUTE(D4,CHAR(13),""),CHAR(10),""),",",REPT(" ",200)),200)))/100,"") | F4: 0.0433 | G4: =IF(ISNUMBER(E4),E4,F4) -> 0.0433 | H4: 08/05/2026
A5: UST 7 Yr | B5: DGS7 | C5: ="https://fred.stlouisfed.org/graph/fredgraph.csv?id="&B5&"&cosd="&TEXT(TODAY()-21,"YYYY-MM-DD") -> https://fred.stlouisfed.org/graph/fredgraph.csv?id=DGS7&cosd=2026-07-15 | D5: =IFERROR(_xludf.webservice(C5),"") | E5: =IFERROR(VALUE(TRIM(RIGHT(SUBSTITUTE(SUBSTITUTE(SUBSTITUTE(D5,CHAR(13),""),CHAR(10),""),",",REPT(" ",200)),200)))/100,"") | F5: 0.0447 | G5: =IF(ISNUMBER(E5),E5,F5) -> 0.0447 | H5: 08/05/2026
A6: UST 10 Yr | B6: DGS10 | C6: ="https://fred.stlouisfed.org/graph/fredgraph.csv?id="&B6&"&cosd="&TEXT(TODAY()-21,"YYYY-MM-DD") -> https://fred.stlouisfed.org/graph/fredgraph.csv?id=DGS10&cosd=2026-07-15 | D6: =IFERROR(_xludf.webservice(C6),"") | E6: =IFERROR(VALUE(TRIM(RIGHT(SUBSTITUTE(SUBSTITUTE(SUBSTITUTE(D6,CHAR(13),""),CHAR(10),""),",",REPT(" ",200)),200)))/100,"") | F6: 0.0463 | G6: =IF(ISNUMBER(E6),E6,F6) -> 0.0463 | H6: 08/05/2026
A7: UST 30 Yr | B7: DGS30 | C7: ="https://fred.stlouisfed.org/graph/fredgraph.csv?id="&B7&"&cosd="&TEXT(TODAY()-21,"YYYY-MM-DD") -> https://fred.stlouisfed.org/graph/fredgraph.csv?id=DGS30&cosd=2026-07-15 | D7: =IFERROR(_xludf.webservice(C7),"") | E7: =IFERROR(VALUE(TRIM(RIGHT(SUBSTITUTE(SUBSTITUTE(SUBSTITUTE(D7,CHAR(13),""),CHAR(10),""),",",REPT(" ",200)),200)))/100,"") | F7: 0.0517 | G7: =IF(ISNUMBER(E7),E7,F7) -> 0.0517 | H7: 08/05/2026
A8: 30-Day Avg SOFR | B8: SOFR30DAYAVG | C8: ="https://fred.stlouisfed.org/graph/fredgraph.csv?id="&B8&"&cosd="&TEXT(TODAY()-21,"YYYY-MM-DD") -> https://fred.stlouisfed.org/graph/fredgraph.csv?id=SOFR30DAYAVG&cosd=2026-07-15 | D8: =IFERROR(_xludf.webservice(C8),"") | E8: =IFERROR(VALUE(TRIM(RIGHT(SUBSTITUTE(SUBSTITUTE(SUBSTITUTE(D8,CHAR(13),""),CHAR(10),""),",",REPT(" ",200)),200)))/100,"") | F8: 0.0362 | G8: =IF(ISNUMBER(E8),E8,F8) -> 0.0362 | H8: 08/04/2026
A9: Fixed (no index) | C9: — | D9: — | E9: — | F9: 0 | G9: =F9 -> 0 | H9: n/a
A11: Sources: FRED series DGS5 / DGS7 / DGS10 / DGS30 / SOFR30DAYAVG (https://fred.stlouisfed.org). Override values: U.S. Treasury Daily Par Yield Curve, 08/05/2026 (home.treasury.gov) and NY Fed 30-Day Average SOFR, 08/04/2026. FRED posts treasury yields with a 1-business-day lag.

Sheet Instructions
A1: HOW THIS WORKBOOK WORKS
A3: Live rates | B3: The Treasury Yields tab pulls the 5/7/10/30-Yr UST and 30-Day Avg SOFR from FRED using =WEBSERVICE(). This works in Excel for Windows (Microsoft 365 / Excel 2013+) with an internet connection. Press Ctrl+Alt+F9 to force a refresh. WEBSERVICE is NOT supported in Excel for Mac, Excel Online, or Google Sheets — there, the workbook automatically falls back to the yellow Manual Override cells.
A4: Fallback logic | B4: RATE USED = the live parsed rate when the web pull succeeds and returns a number; otherwise the Manual Override. FRED posts treasury yields with a ~1-business-day lag; on the rare day the latest FRED row is blank (holiday), the override is used — just update the yellow cells from home.treasury.gov.
A5: Interest rate build-up | B5: On the Loan Terms tab: Interest Rate = Index Rate + Spread (bps) / 10,000. Spreads are placeholders — edit the blue cells to match current lender quotes.
A6: Dropdown lookup | B6: On the Loan Assumptions tab, pick a program in the yellow dropdown (cell C5); LTV, rate, DSCR, IO, term, and amortization populate via INDEX/MATCH. To use the dropdown in your own model, point a data validation list at the named range LenderList and INDEX/MATCH against the Loan Terms tab.
A7: Named ranges | B7: LenderList (program names), LoanTermsTable (full matrix), UST_5Y, UST_7Y, UST_10Y, UST_30Y, SOFR_30D (RATE USED cells) — all available for formulas in other workbooks or added tabs.
A8: Adding a lender | B8: Insert a row inside the Loan Terms table (above the last program row), fill in the blue cells, copy the Index Rate and Interest Rate formulas down, then extend the LenderList / LoanTermsTable named ranges (Formulas > Name Manager) if you inserted at the very bottom.
A9: Color key | B9: Blue font = editable input / placeholder assumption. Black = formula. Green = pulls from another tab. Yellow fill = key user inputs (dropdown, rate overrides).
A10: Example | B10: Fannie Mae — Conventional at a 4.63% 10-Yr UST + 155 bps = 6.18% rate, 75% LTV, 1.25x DSCR, 3 yrs IO, 120-month term, 360-month amortization.
A11: Disclaimer | B11: All terms are indicative placeholders for screening/underwriting, not loan quotes or commitments. Confirm pricing and structure with lenders.
