Workbook
Name GeneratedBy: #REF!
Name masterkeytable: Masterkey!$A$1:$B$50
Name rediq_dealname: 'Trailing Financials'!$A$1
Name rediq_lineitems_overview: 'Trailing Financials'!#REF!

Sheet Trailing Financials
A1: Harvest Moon
A2: Trailing 12 Month Income/Expense
B3: Monthly | C3: Monthly | D3: Monthly | E3: Monthly | F3: Monthly | G3: Monthly | H3: Monthly | I3: Monthly | J3: Monthly | K3: Monthly | L3: Monthly | M3: Monthly
A4: {=Final_T_12[category]} -> Account | B4: {=Final_T_12[date1]} -> 45809 | C4: {=Final_T_12[date2]} -> 45839 | D4: {=Final_T_12[date3]} -> 45870 | E4: {=Final_T_12[date4]} -> 45901 | F4: {=Final_T_12[date5]} -> 45931 | G4: {=Final_T_12[date6]} -> 45962 | H4: {=Final_T_12[date7]} -> 45992 | I4: {=Final_T_12[date8]} -> 46023 | J4: {=Final_T_12[date9]} -> 46054 | K4: {=Final_T_12[date10]} -> 46082 | L4: {=Final_T_12[date11]} -> 46113 | M4: {=Final_T_12[date12]} -> 46143 | N4: {=Final_T_12[total]} -> Total
A6: Rental Income
A7: 4100100 Apartment Income | B7: 98319 | C7: 98319 | D7: 98319 | E7: 98319 | F7: 98319 | G7: 98319 | H7: 98319 | I7: 98319 | J7: 98319 | K7: 98319 | L7: 98319 | M7: 98319 | N7: 1179828
A8: (Loss to Lease) / Gain to Lease
A9: 4100101 Gain/Loss to Lease | B9: -7470 | C9: -5694 | D9: -4199 | E9: -3850 | F9: -4278 | G9: -4164 | H9: -4094 | I9: -5332 | J9: -3695 | K9: -3174 | L9: -3385 | M9: -3248 | N9: -52583
A10: Vacancy
A11: 4100105 Model Units | B11: 0 | C11: 0 | D11: 0 | E11: 0 | F11: 0 | G11: 0 | H11: 0 | I11: 0 | J11: 0 | K11: 0 | L11: -1.83 | M11: -5 | N11: -6.83
A12: Non-Revenue/Concessions
A13: 4100106 Vacancy Loss | B13: -13725.89 | C13: -14532.17 | D13: -25005.29 | E13: -18833.49 | F13: -7135.31 | G13: -3387.5 | H13: -2806.89 | I13: -105.42 | J13: -1181.42 | K13: -2687.1 | L13: -3492.74 | M13: -2583 | N13: -95476.22
A14: 4100107 Concessions | B14: 0 | C14: 0 | D14: 0 | E14: 0 | F14: -99.86 | G14: 0 | H14: 0 | I14: 0 | J14: 0 | K14: 0 | L14: 0 | M14: 0 | N14: -99.86
A15: Bad Debt
A16: 4100112 Net Prepaids | B16: 732.09 | C16: 5.94 | D16: -2385.74 | E16: 789.69 | F16: 1159.41 | G16: -2248.45 | H16: 960.86 | I16: 64.26 | J16: -1337.56 | K16: -133.27 | L16: 865.34 | M16: -785.12 | N16: -2312.55
A17: 4100113 Net Delinquency | B17: -7210.84 | C17: -15776.46 | D17: -13010.57 | E17: 1307.36 | F17: -4534.37 | G17: 2586.83 | H17: -1844.19 | I17: -1177.15 | J17: 428.94 | K17: -1032.18 | L17: 66.59 | M17: -368.77 | N17: -40564.81
A18: RUBS - Water/Sewer
A19: 4101800 Water Reimbursement | B19: 0 | C19: 0 | D19: 0 | E19: 0 | F19: 2670 | G19: 4240 | H19: 4151 | I19: 0 | J19: 0 | K19: 0 | L19: 0 | M19: 0 | N19: 11061
A20: RUBS - Electric/Gas/Other
A21: 4101830 Trash Reimbursement | B21: 1148.04 | C21: 1127.42 | D21: 818.24 | E21: 919.17 | F21: 760.65 | G21: 705.83 | H21: 760 | I21: 0 | J21: 0 | K21: 0 | L21: 0 | M21: 0 | N21: 6239.35
A22: Other Income
A23: Other Income | B23: 0 | C23: 0 | D23: 0 | E23: 0 | F23: 0 | G23: 0 | H23: 0 | I23: 0 | J23: 0 | K23: 0 | L23: 0 | M23: 0 | N23: 0
A24: 4100200 Month to Month | B24: 0 | C24: 0 | D24: 0 | E24: 0 | F24: 135.89 | G24: 400 | H24: 0 | I24: 0 | J24: 0 | K24: 0 | L24: 0 | M24: 0 | N24: 535.89
A25: 4100600 Cleaning fee/Damage Fee | B25: 0 | C25: 0 | D25: 28.7 | E25: 0 | F25: 0 | G25: 0 | H25: 0 | I25: 0 | J25: 0 | K25: 0 | L25: 0 | M25: 0 | N25: 28.7
A26: 4100700 Carport Parking | B26: 105 | C26: 210 | D26: 105 | E26: 141.17 | F26: 210 | G26: 148.17 | H26: 210 | I26: 175 | J26: 140 | K26: 175 | L26: 175 | M26: 175 | N26: 1969.34
A27: 4100800 Pet Fee | B27: 180 | C27: 180 | D27: 135 | E27: 190 | F27: 145.2 | G27: 120 | H27: 120 | I27: 120 | J27: 145 | K27: 160 | L27: 160 | M27: 185 | N27: 1840.2
A28: 4100900 Deposit Forfeiture | B28: 0 | C28: 4500 | D28: 3499 | E28: 350 | F28: 0 | G28: 0 | H28: 0 | I28: 2440 | J28: 0 | K28: 0 | L28: 404.5 | M28: 718.22 | N28: 11911.72
A29: 4101100 Late Charges | B29: 582 | C29: 339.07 | D29: 64.77 | E29: 949.5 | F29: 410 | G29: 1474 | H29: 969 | I29: 1003.8 | J29: 863.5 | K29: 1166.4 | L29: 104.9 | M29: 629.5 | N29: 8556.44
A30: 4101200 NSF Charges | B30: 50 | C30: 0 | D30: 7 | E30: 93 | F30: 0 | G30: 0 | H30: 100 | I30: 200 | J30: 150 | K30: 50 | L30: 50 | M30: 0 | N30: 700
A31: 4101400 Application Fees | B31: 400 | C31: 390 | D31: 149 | E31: 1347 | F31: 660 | G31: 0 | H31: 75 | I31: 0 | J31: 0 | K31: 225 | L31: 375 | M31: 100 | N31: 3721
A32: 4101500 Washer/Dryer Income | B32: 376.07 | C32: 480 | D32: 318.23 | E32: 952.5 | F32: 1135.2 | G32: 1813.87 | H32: 1627.41 | I32: 1850.61 | J32: 1627.42 | K32: 1600.97 | L32: 1633.17 | M32: 1786.45 | N32: 15201.9
A33: 4101600 Administrative Fee | B33: 420 | C33: 0 | D33: 149 | E33: 637 | F33: 400 | G33: 0 | H33: 0 | I33: 110 | J33: 10 | K33: 110 | L33: 300 | M33: -95 | N33: 2041
A34: 4101835 Valet Trash Reimbursement | B34: 44.84 | C34: 125.97 | D34: 251.61 | E34: 619.77 | F34: 834.89 | G34: 1166.5 | H34: 1060.48 | I34: 0 | J34: 0 | K34: 0 | L34: 0 | M34: 0 | N34: 4104.06
... A39: Total Revenue | B39: 74884.47 | C39: 70655.25 | D39: 60080.61 | E39: 85315.94 | F39: 92114.84 | G39: 102675.02 | H39: 101054.77 | I39: 106890.72 | J39: 104771.09 | K39: 103805.77 | L39: 103488.1 | M39: 102709.24 | N39: 1108445.8
A41: Expense
A42: Contract Services
A43: 5500200 Equipment Rental and Expense | B43: 0 | C43: 0 | D43: 0 | E43: 0 | F43: 0 | G43: 0 | H43: 1604.27 | I43: 0 | J43: 0 | K43: 0 | L43: 0 | M43: 392 | N43: 1996.27
A44: 5500300 Landscaping | B44: 811.88 | C44: 811.88 | D44: 811.88 | E44: 811.88 | F44: 811.88 | G44: 811.88 | H44: 811.88 | I44: 811.88 | J44: 811.88 | K44: 811.88 | L44: 811.88 | M44: 811.88 | N44: 9742.56
A45: 5500350 Landscaping Seasonal | B45: 0 | C45: 0 | D45: 447.55 | E45: 0 | F45: 0 | G45: 0 | H45: 0 | I45: 0 | J45: 0 | K45: 0 | L45: 0 | M45: 0 | N45: 447.55
A46: 5500700 Pest Control | B46: 0 | C46: 0 | D46: 107.98 | E46: 0 | F46: 363.97 | G46: 107.98 | H46: 107.98 | I46: 118.78 | J46: 0 | K46: 237.56 | L46: 0 | M46: 237.56 | N46: 1281.81
A47: 5500800 Alarm Monitoring | B47: 0 | C47: 0 | D47: 0 | E47: 0 | F47: 0 | G47: 0 | H47: 584.56 | I47: 0 | J47: 681.99 | K47: 2432.06 | L47: 0 | M47: 1694.8 | N47: 5393.41
A48: 5500900 Washer/Dryer Expense | B48: 1203.2 | C48: 1203.2 | D48: 1203.21 | E48: 4690.54 | F48: 0 | G48: 2063.27 | H48: 0 | I48: 1806.42 | J48: 0 | K48: 1815.35 | L48: 3761.86 | M48: 0 | N48: 17747.05
A49: Repair & Maintenance
A50: 5700100 Carpentry | B50: 0 | C50: 21.62 | D50: 0 | E50: 0 | F50: 0 | G50: 0 | H50: 0 | I50: 0 | J50: 0 | K50: 0 | L50: 0 | M50: -32.12 | N50: -10.5
A51: 5700200 Paint Contract | B51: 1828.3 | C51: 5574.56 | D51: 1910 | E51: 3200.6 | F51: 9664.62 | G51: 2274.8 | H51: 0 | I51: 443.83 | J51: 33.53 | K51: 1010.8 | L51: 2716 | M51: 1377.4 | N51: 30034.44
A52: 5700500 Small Tools | B52: 0 | C52: 260.68 | D52: 0 | E52: 359.23 | F52: 23.71 | G52: 0 | H52: 0 | I52: 0 | J52: 0 | K52: 0 | L52: 0 | M52: 0 | N52: 643.62
A53: 5700700 Electrical Parts and Labor | B53: 63.36 | C53: 92.88 | D53: 0 | E53: 25.94 | F53: 154.66 | G53: 103.4 | H53: 0 | I53: 0 | J53: 94.77 | K53: 12.59 | L53: 0 | M53: 0 | N53: 547.6
A54: 5700900 Air Conditioning and Heat | B54: 0 | C54: 350.02 | D54: 0 | E54: 165.75 | F54: 1213.2 | G54: 283.9 | H54: 496.71 | I54: 583.31 | J54: 158.23 | K54: 1544.37 | L54: 51.96 | M54: 0 | N54: 4847.45
A55: 5701000 Pool Supplies and Repairs | B55: 0 | C55: 180.03 | D55: 0 | E55: 558.27 | F55: 538.9 | G55: 270.62 | H55: 299.13 | I55: 0 | J55: 15.99 | K55: 249.23 | L55: 0 | M55: 968.99 | N55: 3081.16
A56: 5701100 General Supplies | B56: 0 | C56: 0 | D56: 0 | E56: 0 | F56: 0 | G56: 0 | H56: 0 | I56: 0 | J56: 626.6 | K56: 0 | L56: 0 | M56: 0 | N56: 626.6
A57: 5701200 Landscaping Supplies | B57: 0 | C57: 0 | D57: 0 | E57: 351.38 | F57: 10.29 | G57: 0 | H57: 0 | I57: 0 | J57: 0 | K57: 0 | L57: 0 | M57: 0 | N57: 361.67
A58: 5701300 Plumbing Labor and Parts | B58: 72.53 | C58: 767.46 | D58: 0 | E58: 638.51 | F58: -57.85 | G58: 179.37 | H58: 0 | I58: 0 | J58: 240.17 | K58: 467.66 | L58: 45.45 | M58: 0 | N58: 2353.3
A59: 5701600 Glass and Mirror | B59: 0 | C59: 0 | D59: 0 | E59: 0 | F59: 0 | G59: 0 | H59: 0 | I59: 0 | J59: 708.36 | K59: 0 | L59: 0 | M59: 0 | N59: 708.36
A60: 5701700 Driveway and Sidewalk Repairs | B60: 0 | C60: 0 | D60: 0 | E60: 110.22 | F60: 0 | G60: 0 | H60: 0 | I60: 0 | J60: 0 | K60: 0 | L60: 0 | M60: 0 | N60: 110.22
A61: 5701800 Appliance | B61: 672.8 | C61: 483.61 | D61: 0 | E61: 402 | F61: 361.15 | G61: 78.18 | H61: 0 | I61: 0 | J61: 619.35 | K61: 416.09 | L61: 125.12 | M61: 419.02 | N61: 3577.32
... A69: 5709901 Vendor Rebate | B69: 0 | C69: 0 | D69: 0 | E69: 0 | F69: 0 | G69: -88.57 | H69: 0 | I69: 0 | J69: -830.06 | K69: 0 | L69: 0 | M69: -95.17 | N69: -1013.8
A70: Administrative
A71: 5400100 Office Supplies/General | B71: 10.8 | C71: 55.04 | D71: 263.47 | E71: 14.6 | F71: 638.36 | G71: 34.77 | H71: 16.9 | I71: 217.3 | J71: 9.46 | K71: 9.6 | L71: 315.18 | M71: 10 | N71: 1595.48
A72: 5400200 Postage | B72: 0 | C72: 34.12 | D72: 90.12 | E72: 8.76 | F72: 23.68 | G72: 56.94 | H72: 28.57 | I72: 21.5 | J72: 42.99 | K72: 25.07 | L72: 64.13 | M72: 60.83 | N72: 456.71
A73: 5400900 Auto and Travel | B73: 148.74 | C73: 0 | D73: 200 | E73: 385 | F73: 1027.6 | G73: 0 | H73: 0 | I73: 189 | J73: 0 | K73: 837.2 | L73: 249.98 | M73: 0 | N73: 3037.52
A74: 5401000 Dues and Subscription | B74: 55.36 | C74: 0 | D74: 0 | E74: 134.56 | F74: 0 | G74: 0 | H74: 0 | I74: 0 | J74: 0 | K74: 796.31 | L74: 1592.6 | M74: 0 | N74: 2578.83
A75: 5401200 Application Screening | B75: 93.36 | C75: 93.36 | D75: 93.36 | E75: 93.36 | F75: 93.36 | G75: 93.36 | H75: 0 | I75: 6.81 | J75: 0 | K75: 3.2 | L75: 30.44 | M75: 30.44 | N75: 631.05
A76: 5401300 Legal and Professional | B76: 0 | C76: 2482.98 | D76: 0 | E76: 0 | F76: 0 | G76: 0 | H76: 1696.25 | I76: 0 | J76: 0 | K76: 0 | L76: 0 | M76: 0 | N76: 4179.23
A77: 5401400 Evictions | B77: 200 | C77: 188.95 | D77: 0 | E77: 0 | F77: 0 | G77: 0 | H77: 154.22 | I77: 0 | J77: 0 | K77: 0 | L77: 0 | M77: 0 | N77: 543.17
A78: 5401700 Computer Fees/Permits | B78: 728.9 | C78: 27.76 | D78: 904.74 | E78: 872.29 | F78: 223.25 | G78: 101.27 | H78: 218.67 | I78: 2043.21 | J78: 190.01 | K78: 128.95 | L78: 721.66 | M78: 755.99 | N78: 6916.7
A79: 5401900 Bank Charges | B79: 164.7 | C79: 195.23 | D79: 184.09 | E79: 164.41 | F79: 234.88 | G79: 158.2 | H79: 130.54 | I79: 137.27 | J79: 186.47 | K79: 188.54 | L79: 142.34 | M79: 106.75 | N79: 1993.42
A80: 5402000 Employee Relations | B80: 26.52 | C80: 0 | D80: 230.17 | E80: 226.67 | F80: 0 | G80: 0 | H80: 475 | I80: 0 | J80: 0 | K80: 0 | L80: 0 | M80: 0 | N80: 958.36
A81: Marketing
A82: 5600200 Advertising Media | B82: 0 | C82: 0 | D82: 0 | E82: 1377.78 | F82: 908 | G82: 0 | H82: 0 | I82: 0 | J82: 1816 | K82: 0 | L82: 908 | M82: 454 | N82: 5463.78
A83: 5600500 Mini Model | B83: 0 | C83: 0 | D83: 0 | E83: 141.25 | F83: 0 | G83: 0 | H83: 0 | I83: 0 | J83: 0 | K83: 0 | L83: 0 | M83: 0 | N83: 141.25
A84: 5600900 Signs and Banners | B84: 0 | C84: 998.08 | D84: 0 | E84: 0 | F84: 0 | G84: 0 | H84: 0 | I84: 0 | J84: 0 | K84: 0 | L84: 0 | M84: 0 | N84: 998.08
A85: 5610400 Resident Relations | B85: 0 | C85: 0 | D85: 127.55 | E85: 0 | F85: 138.5 | G85: 0 | H85: 0 | I85: 0 | J85: 250 | K85: 0 | L85: 0 | M85: 0 | N85: 516.05
A86: 5610600 Marketing Materials | B86: 0 | C86: 473.05 | D86: 127.55 | E86: 0 | F86: 37.49 | G86: 0 | H86: 0 | I86: 0 | J86: 0 | K86: 0 | L86: 0 | M86: 0 | N86: 638.09
A87: Payroll
A88: 5100100 Managers and Assistants | B88: 1341.2 | C88: 1152.2 | D88: 4463.55 | E88: 3231.2 | F88: 3735.21 | G88: 3939.96 | H88: 3627.58 | I88: 5111.93 | J88: 3638.08 | K88: 4464.96 | L88: 3900.58 | M88: 2535.58 | N88: 41142.03
A89: 5100200 Leasing | B89: 0 | C89: 0 | D89: 0 | E89: 0 | F89: 0 | G89: 1277.72 | H89: 0 | I89: 0 | J89: 0 | K89: 0 | L89: 0 | M89: 0 | N89: 1277.72
A90: 5100600 General Maintenance Salaries | B90: 0 | C90: 769.45 | D90: 454.35 | E90: 1214.27 | F90: 214.5 | G90: 3322.8 | H90: 1238.45 | I90: 0 | J90: 390 | K90: 2930.13 | L90: 0 | M90: 1733.56 | N90: 12267.51
A91: 5100900 Incentives | B91: 0 | C91: 400 | D91: 0 | E91: 1800 | F91: 1100 | G91: 600 | H91: 300 | I91: 0 | J91: 480 | K91: 1080 | L91: 120 | M91: 135 | N91: 6015
A92: 5280000 Payroll Taxes | B92: 153.51 | C92: 178.7 | D92: 350.5 | E92: 423.56 | F92: 380.46 | G92: 341.75 | H92: 271.95 | I92: 666.79 | J92: 520.01 | K92: 435.68 | L92: 300.16 | M92: 200.95 | N92: 4224.02
A93: 5280100 Workers Compensation | B93: 23.36 | C93: 2.14 | D93: 2.48 | E93: 7.11 | F93: 27.14 | G93: 14.83 | H93: 7.24 | I93: 5.79 | J93: 4.76 | K93: 19.42 | L93: 18.13 | M93: 9.49 | N93: 141.89
A94: Water/Sewer
A95: 5800300 Water | B95: 6843.75 | C95: 5492.7 | D95: 5674.43 | E95: 5635.35 | F95: 6209.14 | G95: 5149.47 | H95: 5405.45 | I95: 5337.29 | J95: 5551.64 | K95: 5448.33 | L95: 5432.76 | M95: 5831.32 | N95: 68011.63
A96: Trash
A97: 5800400 Trash Removal | B97: 0 | C97: 1518 | D97: 2418 | E97: 1518 | F97: 2440.55 | G97: 1518 | H97: 1624.2 | I97: 1624.2 | J97: 2629.26 | K97: 1624.2 | L97: 1624 | M97: 1624.2 | N97: 20162.61
A98: 5800401 Valet Trash | B98: 856.6 | C98: 2550.79 | D98: 0 | E98: 772.55 | F98: 772.55 | G98: 918.53 | H98: 918.53 | I98: 263.47 | J98: 830.06 | K98: 200 | L98: 1080.06 | M98: 968.53 | N98: 10131.67
A99: Electric
A100: 5800100 Electricity | B100: 618.3 | C100: 552.71 | D100: 638.36 | E100: 347.37 | F100: 648.03 | G100: 582.23 | H100: 513.13 | I100: 648.6 | J100: 622.88 | K100: 522.52 | L100: 517.48 | M100: 673.93 | N100: 6885.54
A101: 5800101 Electricity - Vacant | B101: 579.94 | C101: 830.21 | D101: 962.24 | E101: 1640.88 | F101: 866.55 | G101: 1067.5 | H101: 512.09 | I101: 196.11 | J101: -858.19 | K101: 422.7 | L101: 261.8 | M101: 241.75 | N101: 6723.58
A102: Gas/Other
A103: 5800500 Telephone | B103: 100.28 | C103: 73.87 | D103: 73.63 | E103: 59.92 | F103: 60.28 | G103: 480.09 | H103: 60.34 | I103: 60.34 | J103: 60.33 | K103: 60.33 | L103: 60.33 | M103: 280.79 | N103: 1430.53
A104: Management Fee
A105: 5900100 Management Fees | B105: 2995.38 | C105: 2826.21 | D105: 2403.22 | E105: 3412.64 | F105: 3684.59 | G105: 4107 | H105: 4022.19 | I105: 4275.63 | J105: 4190.84 | K105: 4152.23 | L105: 4019.53 | M105: 4028.37 | N105: 44117.83
A106: Insurance
A107: 6300100 Insurance | B107: 0 | C107: 0 | D107: 0 | E107: 0 | F107: 0 | G107: 0 | H107: 0 | I107: 3346.78 | J107: 3346.78 | K107: 3346.78 | L107: 3346.78 | M107: 3346.78 | N107: 16733.9
A108: Real Estate Taxes
A109: 6200100 Property Taxes | B109: 7867.13 | C109: 7867.13 | D109: 7867.13 | E109: 7867.13 | F109: 7867.13 | G109: 7867.13 | H109: 21857.1 | I109: 9033 | J109: 9033 | K109: 9033 | L109: 9033 | M109: 9033 | N109: 114224.88
A110: Total Expense | B110: 28395.29 | C110: 40113.74 | D110: 33884.98 | E110: 44985.02 | F110: 45515.57 | G110: 42881.02 | H110: 47566.48 | I110: 36949.24 | J110: 36669.87 | K110: 44844.48 | L110: 42761.07 | M110: 38450.38 | N110: 483017.14
A112: Net Operating Income | B112: 46489.18 | C112: 30541.51 | D112: 26195.63 | E112: 40330.92 | F112: 46599.27 | G112: 59794 | H112: 53488.29 | I112: 69941.48 | J112: 68101.22 | K112: 58961.29 | L112: 60727.03 | M112: 64258.86 | N112: 625428.68
B301: =IF(ISBLANK('Final T-12'!BN297),"",'Final T-12'!BN297) | C301: =IF(ISBLANK('Final T-12'!BO297),"",'Final T-12'!BO297) | D301: =IF(ISBLANK('Final T-12'!BP297),"",'Final T-12'!BP297) | E301: =IF(ISBLANK('Final T-12'!BQ297),"",'Final T-12'!BQ297) | F301: =IF(ISBLANK('Final T-12'!BR297),"",'Final T-12'!BR297) | G301: =IF(ISBLANK('Final T-12'!BS297),"",'Final T-12'!BS297) | H301: =IF(ISBLANK('Final T-12'!BT297),"",'Final T-12'!BT297) | I301: =IF(ISBLANK('Final T-12'!BU297),"",'Final T-12'!BU297) | ... N301: =IF(ISBLANK('Final T-12'!BZ297),"",'Final T-12'!BZ297)
B302: =IF(ISBLANK('Final T-12'!BN298),"",'Final T-12'!BN298) | C302: =IF(ISBLANK('Final T-12'!BO298),"",'Final T-12'!BO298) | D302: =IF(ISBLANK('Final T-12'!BP298),"",'Final T-12'!BP298) | E302: =IF(ISBLANK('Final T-12'!BQ298),"",'Final T-12'!BQ298) | F302: =IF(ISBLANK('Final T-12'!BR298),"",'Final T-12'!BR298) | G302: =IF(ISBLANK('Final T-12'!BS298),"",'Final T-12'!BS298) | H302: =IF(ISBLANK('Final T-12'!BT298),"",'Final T-12'!BT298) | I302: =IF(ISBLANK('Final T-12'!BU298),"",'Final T-12'!BU298) | ... N302: =IF(ISBLANK('Final T-12'!BZ298),"",'Final T-12'!BZ298)

Sheet RawData
B1: Total Revenue Check | C1: =SUMIFS(C6:C1041,$A$6:$A$1041,"r")+SUMIFS(C6:C1041,$A$6:$A$1041,"ll")+SUMIFS(C6:C1041,$A$6:$A$1041,"bd")+SUMIFS(C6:C1041,$A$6:$A$1041,"v")+SUMIFS(C6:C1041,$A$6:$A$1041,"nr")+SUMIFS(C6:C1041,$A$6:$A$1041,"oi")+SUMIFS(C6:C1041,$A$6:$A$1041,"rt")+SUMIFS(C6:C1041,$A$6:$A$1041,"ro")+SUMIFS(C6:C1041,$A$6:$A$1041,"rw")-SUMIFS(C6:C1041,$A$6:$A$1041,"rev") -> 0 | D1: =SUMIFS(D6:D1041,$A$6:$A$1041,"r")+SUMIFS(D6:D1041,$A$6:$A$1041,"ll")+SUMIFS(D6:D1041,$A$6:$A$1041,"bd")+SUMIFS(D6:D1041,$A$6:$A$1041,"v")+SUMIFS(D6:D1041,$A$6:$A$1041,"nr")+SUMIFS(D6:D1041,$A$6:$A$1041,"oi")+SUMIFS(D6:D1041,$A$6:$A$1041,"rt")+SUMIFS(D6:D1041,$A$6:$A$1041,"ro")+SUMIFS(D6:D1041,$A$6:$A$1041,"rw")-SUMIFS(D6:D1041,$A$6:$A$1041,"rev") -> 0 | E1: =SUMIFS(E6:E1041,$A$6:$A$1041,"r")+SUMIFS(E6:E1041,$A$6:$A$1041,"ll")+SUMIFS(E6:E1041,$A$6:$A$1041,"bd")+SUMIFS(E6:E1041,$A$6:$A$1041,"v")+SUMIFS(E6:E1041,$A$6:$A$1041,"nr")+SUMIFS(E6:E1041,$A$6:$A$1041,"oi")+SUMIFS(E6:E1041,$A$6:$A$1041,"rt")+SUMIFS(E6:E1041,$A$6:$A$1041,"ro")+SUMIFS(E6:E1041,$A$6:$A$1041,"rw")-SUMIFS(E6:E1041,$A$6:$A$1041,"rev") -> 0 | F1: =SUMIFS(F6:F1041,$A$6:$A$1041,"r")+SUMIFS(F6:F1041,$A$6:$A$1041,"ll")+SUMIFS(F6:F1041,$A$6:$A$1041,"bd")+SUMIFS(F6:F1041,$A$6:$A$1041,"v")+SUMIFS(F6:F1041,$A$6:$A$1041,"nr")+SUMIFS(F6:F1041,$A$6:$A$1041,"oi")+SUMIFS(F6:F1041,$A$6:$A$1041,"rt")+SUMIFS(F6:F1041,$A$6:$A$1041,"ro")+SUMIFS(F6:F1041,$A$6:$A$1041,"rw")-SUMIFS(F6:F1041,$A$6:$A$1041,"rev") -> 0 | G1: =SUMIFS(G6:G1041,$A$6:$A$1041,"r")+SUMIFS(G6:G1041,$A$6:$A$1041,"ll")+SUMIFS(G6:G1041,$A$6:$A$1041,"bd")+SUMIFS(G6:G1041,$A$6:$A$1041,"v")+SUMIFS(G6:G1041,$A$6:$A$1041,"nr")+SUMIFS(G6:G1041,$A$6:$A$1041,"oi")+SUMIFS(G6:G1041,$A$6:$A$1041,"rt")+SUMIFS(G6:G1041,$A$6:$A$1041,"ro")+SUMIFS(G6:G1041,$A$6:$A$1041,"rw")-SUMIFS(G6:G1041,$A$6:$A$1041,"rev") -> 0 | H1: =SUMIFS(H6:H1041,$A$6:$A$1041,"r")+SUMIFS(H6:H1041,$A$6:$A$1041,"ll")+SUMIFS(H6:H1041,$A$6:$A$1041,"bd")+SUMIFS(H6:H1041,$A$6:$A$1041,"v")+SUMIFS(H6:H1041,$A$6:$A$1041,"nr")+SUMIFS(H6:H1041,$A$6:$A$1041,"oi")+SUMIFS(H6:H1041,$A$6:$A$1041,"rt")+SUMIFS(H6:H1041,$A$6:$A$1041,"ro")+SUMIFS(H6:H1041,$A$6:$A$1041,"rw")-SUMIFS(H6:H1041,$A$6:$A$1041,"rev") -> 0 | I1: =SUMIFS(I6:I1041,$A$6:$A$1041,"r")+SUMIFS(I6:I1041,$A$6:$A$1041,"ll")+SUMIFS(I6:I1041,$A$6:$A$1041,"bd")+SUMIFS(I6:I1041,$A$6:$A$1041,"v")+SUMIFS(I6:I1041,$A$6:$A$1041,"nr")+SUMIFS(I6:I1041,$A$6:$A$1041,"oi")+SUMIFS(I6:I1041,$A$6:$A$1041,"rt")+SUMIFS(I6:I1041,$A$6:$A$1041,"ro")+SUMIFS(I6:I1041,$A$6:$A$1041,"rw")-SUMIFS(I6:I1041,$A$6:$A$1041,"rev") -> 0 | J1: =SUMIFS(J6:J1041,$A$6:$A$1041,"r")+SUMIFS(J6:J1041,$A$6:$A$1041,"ll")+SUMIFS(J6:J1041,$A$6:$A$1041,"bd")+SUMIFS(J6:J1041,$A$6:$A$1041,"v")+SUMIFS(J6:J1041,$A$6:$A$1041,"nr")+SUMIFS(J6:J1041,$A$6:$A$1041,"oi")+SUMIFS(J6:J1041,$A$6:$A$1041,"rt")+SUMIFS(J6:J1041,$A$6:$A$1041,"ro")+SUMIFS(J6:J1041,$A$6:$A$1041,"rw")-SUMIFS(J6:J1041,$A$6:$A$1041,"rev") -> 0 | ... O1: =SUMIFS(O6:O1041,$A$6:$A$1041,"r")+SUMIFS(O6:O1041,$A$6:$A$1041,"ll")+SUMIFS(O6:O1041,$A$6:$A$1041,"bd")+SUMIFS(O6:O1041,$A$6:$A$1041,"v")+SUMIFS(O6:O1041,$A$6:$A$1041,"nr")+SUMIFS(O6:O1041,$A$6:$A$1041,"oi")+SUMIFS(O6:O1041,$A$6:$A$1041,"rt")+SUMIFS(O6:O1041,$A$6:$A$1041,"ro")+SUMIFS(O6:O1041,$A$6:$A$1041,"rw")-SUMIFS(O6:O1041,$A$6:$A$1041,"rev") -> 0 | Q1: should be 0
B2: Expense Check | C2: =SUMIFS(C6:C1041,$A$6:$A$1041,"ad")+SUMIFS(C6:C1041,$A$6:$A$1041,"m")+SUMIFS(C6:C1041,$A$6:$A$1041,"cs")+SUMIFS(C6:C1041,$A$6:$A$1041,"rm")+SUMIFS(C6:C1041,$A$6:$A$1041,"pr")+SUMIFS(C6:C1041,$A$6:$A$1041,"e")+SUMIFS(C6:C1041,$A$6:$A$1041,"w")+SUMIFS(C6:C1041,$A$6:$A$1041,"o")+SUMIFS(C6:C1041,$A$6:$A$1041,"tr")+SUMIFS(C6:C1041,$A$6:$A$1041,"i")+SUMIFS(C6:C1041,$A$6:$A$1041,"tx")+SUMIFS(C6:C1041,$A$6:$A$1041,"mf")-SUMIFS(C6:C1041,$A$6:$A$1041,"exp") -> 0 | D2: =SUMIFS(D6:D1041,$A$6:$A$1041,"ad")+SUMIFS(D6:D1041,$A$6:$A$1041,"m")+SUMIFS(D6:D1041,$A$6:$A$1041,"cs")+SUMIFS(D6:D1041,$A$6:$A$1041,"rm")+SUMIFS(D6:D1041,$A$6:$A$1041,"pr")+SUMIFS(D6:D1041,$A$6:$A$1041,"e")+SUMIFS(D6:D1041,$A$6:$A$1041,"w")+SUMIFS(D6:D1041,$A$6:$A$1041,"o")+SUMIFS(D6:D1041,$A$6:$A$1041,"tr")+SUMIFS(D6:D1041,$A$6:$A$1041,"i")+SUMIFS(D6:D1041,$A$6:$A$1041,"tx")+SUMIFS(D6:D1041,$A$6:$A$1041,"mf")-SUMIFS(D6:D1041,$A$6:$A$1041,"exp") -> 0 | E2: =SUMIFS(E6:E1041,$A$6:$A$1041,"ad")+SUMIFS(E6:E1041,$A$6:$A$1041,"m")+SUMIFS(E6:E1041,$A$6:$A$1041,"cs")+SUMIFS(E6:E1041,$A$6:$A$1041,"rm")+SUMIFS(E6:E1041,$A$6:$A$1041,"pr")+SUMIFS(E6:E1041,$A$6:$A$1041,"e")+SUMIFS(E6:E1041,$A$6:$A$1041,"w")+SUMIFS(E6:E1041,$A$6:$A$1041,"o")+SUMIFS(E6:E1041,$A$6:$A$1041,"tr")+SUMIFS(E6:E1041,$A$6:$A$1041,"i")+SUMIFS(E6:E1041,$A$6:$A$1041,"tx")+SUMIFS(E6:E1041,$A$6:$A$1041,"mf")-SUMIFS(E6:E1041,$A$6:$A$1041,"exp") -> 0 | F2: =SUMIFS(F6:F1041,$A$6:$A$1041,"ad")+SUMIFS(F6:F1041,$A$6:$A$1041,"m")+SUMIFS(F6:F1041,$A$6:$A$1041,"cs")+SUMIFS(F6:F1041,$A$6:$A$1041,"rm")+SUMIFS(F6:F1041,$A$6:$A$1041,"pr")+SUMIFS(F6:F1041,$A$6:$A$1041,"e")+SUMIFS(F6:F1041,$A$6:$A$1041,"w")+SUMIFS(F6:F1041,$A$6:$A$1041,"o")+SUMIFS(F6:F1041,$A$6:$A$1041,"tr")+SUMIFS(F6:F1041,$A$6:$A$1041,"i")+SUMIFS(F6:F1041,$A$6:$A$1041,"tx")+SUMIFS(F6:F1041,$A$6:$A$1041,"mf")-SUMIFS(F6:F1041,$A$6:$A$1041,"exp") -> 0 | G2: =SUMIFS(G6:G1041,$A$6:$A$1041,"ad")+SUMIFS(G6:G1041,$A$6:$A$1041,"m")+SUMIFS(G6:G1041,$A$6:$A$1041,"cs")+SUMIFS(G6:G1041,$A$6:$A$1041,"rm")+SUMIFS(G6:G1041,$A$6:$A$1041,"pr")+SUMIFS(G6:G1041,$A$6:$A$1041,"e")+SUMIFS(G6:G1041,$A$6:$A$1041,"w")+SUMIFS(G6:G1041,$A$6:$A$1041,"o")+SUMIFS(G6:G1041,$A$6:$A$1041,"tr")+SUMIFS(G6:G1041,$A$6:$A$1041,"i")+SUMIFS(G6:G1041,$A$6:$A$1041,"tx")+SUMIFS(G6:G1041,$A$6:$A$1041,"mf")-SUMIFS(G6:G1041,$A$6:$A$1041,"exp") -> 0 | H2: =SUMIFS(H6:H1041,$A$6:$A$1041,"ad")+SUMIFS(H6:H1041,$A$6:$A$1041,"m")+SUMIFS(H6:H1041,$A$6:$A$1041,"cs")+SUMIFS(H6:H1041,$A$6:$A$1041,"rm")+SUMIFS(H6:H1041,$A$6:$A$1041,"pr")+SUMIFS(H6:H1041,$A$6:$A$1041,"e")+SUMIFS(H6:H1041,$A$6:$A$1041,"w")+SUMIFS(H6:H1041,$A$6:$A$1041,"o")+SUMIFS(H6:H1041,$A$6:$A$1041,"tr")+SUMIFS(H6:H1041,$A$6:$A$1041,"i")+SUMIFS(H6:H1041,$A$6:$A$1041,"tx")+SUMIFS(H6:H1041,$A$6:$A$1041,"mf")-SUMIFS(H6:H1041,$A$6:$A$1041,"exp") -> 0 | I2: =SUMIFS(I6:I1041,$A$6:$A$1041,"ad")+SUMIFS(I6:I1041,$A$6:$A$1041,"m")+SUMIFS(I6:I1041,$A$6:$A$1041,"cs")+SUMIFS(I6:I1041,$A$6:$A$1041,"rm")+SUMIFS(I6:I1041,$A$6:$A$1041,"pr")+SUMIFS(I6:I1041,$A$6:$A$1041,"e")+SUMIFS(I6:I1041,$A$6:$A$1041,"w")+SUMIFS(I6:I1041,$A$6:$A$1041,"o")+SUMIFS(I6:I1041,$A$6:$A$1041,"tr")+SUMIFS(I6:I1041,$A$6:$A$1041,"i")+SUMIFS(I6:I1041,$A$6:$A$1041,"tx")+SUMIFS(I6:I1041,$A$6:$A$1041,"mf")-SUMIFS(I6:I1041,$A$6:$A$1041,"exp") -> 0 | J2: =SUMIFS(J6:J1041,$A$6:$A$1041,"ad")+SUMIFS(J6:J1041,$A$6:$A$1041,"m")+SUMIFS(J6:J1041,$A$6:$A$1041,"cs")+SUMIFS(J6:J1041,$A$6:$A$1041,"rm")+SUMIFS(J6:J1041,$A$6:$A$1041,"pr")+SUMIFS(J6:J1041,$A$6:$A$1041,"e")+SUMIFS(J6:J1041,$A$6:$A$1041,"w")+SUMIFS(J6:J1041,$A$6:$A$1041,"o")+SUMIFS(J6:J1041,$A$6:$A$1041,"tr")+SUMIFS(J6:J1041,$A$6:$A$1041,"i")+SUMIFS(J6:J1041,$A$6:$A$1041,"tx")+SUMIFS(J6:J1041,$A$6:$A$1041,"mf")-SUMIFS(J6:J1041,$A$6:$A$1041,"exp") -> 0 | ... O2: =SUMIFS(O6:O1041,$A$6:$A$1041,"ad")+SUMIFS(O6:O1041,$A$6:$A$1041,"m")+SUMIFS(O6:O1041,$A$6:$A$1041,"cs")+SUMIFS(O6:O1041,$A$6:$A$1041,"rm")+SUMIFS(O6:O1041,$A$6:$A$1041,"pr")+SUMIFS(O6:O1041,$A$6:$A$1041,"e")+SUMIFS(O6:O1041,$A$6:$A$1041,"w")+SUMIFS(O6:O1041,$A$6:$A$1041,"o")+SUMIFS(O6:O1041,$A$6:$A$1041,"tr")+SUMIFS(O6:O1041,$A$6:$A$1041,"i")+SUMIFS(O6:O1041,$A$6:$A$1041,"tx")+SUMIFS(O6:O1041,$A$6:$A$1041,"mf")-SUMIFS(O6:O1041,$A$6:$A$1041,"exp") -> 0
B3: NOI Check | C3: =(SUMIFS(C6:C1041,$A$6:$A$1041,"r")+SUMIFS(C6:C1041,$A$6:$A$1041,"ll")+SUMIFS(C6:C1041,$A$6:$A$1041,"bd")+SUMIFS(C6:C1041,$A$6:$A$1041,"v")+SUMIFS(C6:C1041,$A$6:$A$1041,"nr")+SUMIFS(C6:C1041,$A$6:$A$1041,"oi")+SUMIFS(C6:C1041,$A$6:$A$1041,"rt")+SUMIFS(C6:C1041,$A$6:$A$1041,"ro")+SUMIFS(C6:C1041,$A$6:$A$1041,"rw"))-(SUMIFS(C6:C1041,$A$6:$A$1041,"ad")+SUMIFS(C6:C1041,$A$6:$A$1041,"m")+SUMIFS(C6:C1041,$A$6:$A$1041,"cs")+SUMIFS(C6:C1041,$A$6:$A$1041,"rm")+SUMIFS(C6:C1041,$A$6:$A$1041,"pr")+SUMIFS(C6:C1041,$A$6:$A$1041,"e")+SUMIFS(C6:C1041,$A$6:$A$1041,"w")+SUMIFS(C6:C1041,$A$6:$A$1041,"o")+SUMIFS(C6:C1041,$A$6:$A$1041,"tr")+SUMIFS(C6:C1041,$A$6:$A$1041,"i")+SUMIFS(C6:C1041,$A$6:$A$1041,"tx")+SUMIFS(C6:C1041,$A$6:$A$1041,"mf"))-SUMIFS(C6:C1041,$A$6:$A$1041,"noi") -> 0 | D3: =(SUMIFS(D6:D1041,$A$6:$A$1041,"r")+SUMIFS(D6:D1041,$A$6:$A$1041,"ll")+SUMIFS(D6:D1041,$A$6:$A$1041,"bd")+SUMIFS(D6:D1041,$A$6:$A$1041,"v")+SUMIFS(D6:D1041,$A$6:$A$1041,"nr")+SUMIFS(D6:D1041,$A$6:$A$1041,"oi")+SUMIFS(D6:D1041,$A$6:$A$1041,"rt")+SUMIFS(D6:D1041,$A$6:$A$1041,"ro")+SUMIFS(D6:D1041,$A$6:$A$1041,"rw"))-(SUMIFS(D6:D1041,$A$6:$A$1041,"ad")+SUMIFS(D6:D1041,$A$6:$A$1041,"m")+SUMIFS(D6:D1041,$A$6:$A$1041,"cs")+SUMIFS(D6:D1041,$A$6:$A$1041,"rm")+SUMIFS(D6:D1041,$A$6:$A$1041,"pr")+SUMIFS(D6:D1041,$A$6:$A$1041,"e")+SUMIFS(D6:D1041,$A$6:$A$1041,"w")+SUMIFS(D6:D1041,$A$6:$A$1041,"o")+SUMIFS(D6:D1041,$A$6:$A$1041,"tr")+SUMIFS(D6:D1041,$A$6:$A$1041,"i")+SUMIFS(D6:D1041,$A$6:$A$1041,"tx")+SUMIFS(D6:D1041,$A$6:$A$1041,"mf"))-SUMIFS(D6:D1041,$A$6:$A$1041,"noi") -> 0 | E3: =(SUMIFS(E6:E1041,$A$6:$A$1041,"r")+SUMIFS(E6:E1041,$A$6:$A$1041,"ll")+SUMIFS(E6:E1041,$A$6:$A$1041,"bd")+SUMIFS(E6:E1041,$A$6:$A$1041,"v")+SUMIFS(E6:E1041,$A$6:$A$1041,"nr")+SUMIFS(E6:E1041,$A$6:$A$1041,"oi")+SUMIFS(E6:E1041,$A$6:$A$1041,"rt")+SUMIFS(E6:E1041,$A$6:$A$1041,"ro")+SUMIFS(E6:E1041,$A$6:$A$1041,"rw"))-(SUMIFS(E6:E1041,$A$6:$A$1041,"ad")+SUMIFS(E6:E1041,$A$6:$A$1041,"m")+SUMIFS(E6:E1041,$A$6:$A$1041,"cs")+SUMIFS(E6:E1041,$A$6:$A$1041,"rm")+SUMIFS(E6:E1041,$A$6:$A$1041,"pr")+SUMIFS(E6:E1041,$A$6:$A$1041,"e")+SUMIFS(E6:E1041,$A$6:$A$1041,"w")+SUMIFS(E6:E1041,$A$6:$A$1041,"o")+SUMIFS(E6:E1041,$A$6:$A$1041,"tr")+SUMIFS(E6:E1041,$A$6:$A$1041,"i")+SUMIFS(E6:E1041,$A$6:$A$1041,"tx")+SUMIFS(E6:E1041,$A$6:$A$1041,"mf"))-SUMIFS(E6:E1041,$A$6:$A$1041,"noi") -> 0 | F3: =(SUMIFS(F6:F1041,$A$6:$A$1041,"r")+SUMIFS(F6:F1041,$A$6:$A$1041,"ll")+SUMIFS(F6:F1041,$A$6:$A$1041,"bd")+SUMIFS(F6:F1041,$A$6:$A$1041,"v")+SUMIFS(F6:F1041,$A$6:$A$1041,"nr")+SUMIFS(F6:F1041,$A$6:$A$1041,"oi")+SUMIFS(F6:F1041,$A$6:$A$1041,"rt")+SUMIFS(F6:F1041,$A$6:$A$1041,"ro")+SUMIFS(F6:F1041,$A$6:$A$1041,"rw"))-(SUMIFS(F6:F1041,$A$6:$A$1041,"ad")+SUMIFS(F6:F1041,$A$6:$A$1041,"m")+SUMIFS(F6:F1041,$A$6:$A$1041,"cs")+SUMIFS(F6:F1041,$A$6:$A$1041,"rm")+SUMIFS(F6:F1041,$A$6:$A$1041,"pr")+SUMIFS(F6:F1041,$A$6:$A$1041,"e")+SUMIFS(F6:F1041,$A$6:$A$1041,"w")+SUMIFS(F6:F1041,$A$6:$A$1041,"o")+SUMIFS(F6:F1041,$A$6:$A$1041,"tr")+SUMIFS(F6:F1041,$A$6:$A$1041,"i")+SUMIFS(F6:F1041,$A$6:$A$1041,"tx")+SUMIFS(F6:F1041,$A$6:$A$1041,"mf"))-SUMIFS(F6:F1041,$A$6:$A$1041,"noi") -> 0 | G3: =(SUMIFS(G6:G1041,$A$6:$A$1041,"r")+SUMIFS(G6:G1041,$A$6:$A$1041,"ll")+SUMIFS(G6:G1041,$A$6:$A$1041,"bd")+SUMIFS(G6:G1041,$A$6:$A$1041,"v")+SUMIFS(G6:G1041,$A$6:$A$1041,"nr")+SUMIFS(G6:G1041,$A$6:$A$1041,"oi")+SUMIFS(G6:G1041,$A$6:$A$1041,"rt")+SUMIFS(G6:G1041,$A$6:$A$1041,"ro")+SUMIFS(G6:G1041,$A$6:$A$1041,"rw"))-(SUMIFS(G6:G1041,$A$6:$A$1041,"ad")+SUMIFS(G6:G1041,$A$6:$A$1041,"m")+SUMIFS(G6:G1041,$A$6:$A$1041,"cs")+SUMIFS(G6:G1041,$A$6:$A$1041,"rm")+SUMIFS(G6:G1041,$A$6:$A$1041,"pr")+SUMIFS(G6:G1041,$A$6:$A$1041,"e")+SUMIFS(G6:G1041,$A$6:$A$1041,"w")+SUMIFS(G6:G1041,$A$6:$A$1041,"o")+SUMIFS(G6:G1041,$A$6:$A$1041,"tr")+SUMIFS(G6:G1041,$A$6:$A$1041,"i")+SUMIFS(G6:G1041,$A$6:$A$1041,"tx")+SUMIFS(G6:G1041,$A$6:$A$1041,"mf"))-SUMIFS(G6:G1041,$A$6:$A$1041,"noi") -> 0 | H3: =(SUMIFS(H6:H1041,$A$6:$A$1041,"r")+SUMIFS(H6:H1041,$A$6:$A$1041,"ll")+SUMIFS(H6:H1041,$A$6:$A$1041,"bd")+SUMIFS(H6:H1041,$A$6:$A$1041,"v")+SUMIFS(H6:H1041,$A$6:$A$1041,"nr")+SUMIFS(H6:H1041,$A$6:$A$1041,"oi")+SUMIFS(H6:H1041,$A$6:$A$1041,"rt")+SUMIFS(H6:H1041,$A$6:$A$1041,"ro")+SUMIFS(H6:H1041,$A$6:$A$1041,"rw"))-(SUMIFS(H6:H1041,$A$6:$A$1041,"ad")+SUMIFS(H6:H1041,$A$6:$A$1041,"m")+SUMIFS(H6:H1041,$A$6:$A$1041,"cs")+SUMIFS(H6:H1041,$A$6:$A$1041,"rm")+SUMIFS(H6:H1041,$A$6:$A$1041,"pr")+SUMIFS(H6:H1041,$A$6:$A$1041,"e")+SUMIFS(H6:H1041,$A$6:$A$1041,"w")+SUMIFS(H6:H1041,$A$6:$A$1041,"o")+SUMIFS(H6:H1041,$A$6:$A$1041,"tr")+SUMIFS(H6:H1041,$A$6:$A$1041,"i")+SUMIFS(H6:H1041,$A$6:$A$1041,"tx")+SUMIFS(H6:H1041,$A$6:$A$1041,"mf"))-SUMIFS(H6:H1041,$A$6:$A$1041,"noi") -> 0 | I3: =(SUMIFS(I6:I1041,$A$6:$A$1041,"r")+SUMIFS(I6:I1041,$A$6:$A$1041,"ll")+SUMIFS(I6:I1041,$A$6:$A$1041,"bd")+SUMIFS(I6:I1041,$A$6:$A$1041,"v")+SUMIFS(I6:I1041,$A$6:$A$1041,"nr")+SUMIFS(I6:I1041,$A$6:$A$1041,"oi")+SUMIFS(I6:I1041,$A$6:$A$1041,"rt")+SUMIFS(I6:I1041,$A$6:$A$1041,"ro")+SUMIFS(I6:I1041,$A$6:$A$1041,"rw"))-(SUMIFS(I6:I1041,$A$6:$A$1041,"ad")+SUMIFS(I6:I1041,$A$6:$A$1041,"m")+SUMIFS(I6:I1041,$A$6:$A$1041,"cs")+SUMIFS(I6:I1041,$A$6:$A$1041,"rm")+SUMIFS(I6:I1041,$A$6:$A$1041,"pr")+SUMIFS(I6:I1041,$A$6:$A$1041,"e")+SUMIFS(I6:I1041,$A$6:$A$1041,"w")+SUMIFS(I6:I1041,$A$6:$A$1041,"o")+SUMIFS(I6:I1041,$A$6:$A$1041,"tr")+SUMIFS(I6:I1041,$A$6:$A$1041,"i")+SUMIFS(I6:I1041,$A$6:$A$1041,"tx")+SUMIFS(I6:I1041,$A$6:$A$1041,"mf"))-SUMIFS(I6:I1041,$A$6:$A$1041,"noi") -> 0 | J3: =(SUMIFS(J6:J1041,$A$6:$A$1041,"r")+SUMIFS(J6:J1041,$A$6:$A$1041,"ll")+SUMIFS(J6:J1041,$A$6:$A$1041,"bd")+SUMIFS(J6:J1041,$A$6:$A$1041,"v")+SUMIFS(J6:J1041,$A$6:$A$1041,"nr")+SUMIFS(J6:J1041,$A$6:$A$1041,"oi")+SUMIFS(J6:J1041,$A$6:$A$1041,"rt")+SUMIFS(J6:J1041,$A$6:$A$1041,"ro")+SUMIFS(J6:J1041,$A$6:$A$1041,"rw"))-(SUMIFS(J6:J1041,$A$6:$A$1041,"ad")+SUMIFS(J6:J1041,$A$6:$A$1041,"m")+SUMIFS(J6:J1041,$A$6:$A$1041,"cs")+SUMIFS(J6:J1041,$A$6:$A$1041,"rm")+SUMIFS(J6:J1041,$A$6:$A$1041,"pr")+SUMIFS(J6:J1041,$A$6:$A$1041,"e")+SUMIFS(J6:J1041,$A$6:$A$1041,"w")+SUMIFS(J6:J1041,$A$6:$A$1041,"o")+SUMIFS(J6:J1041,$A$6:$A$1041,"tr")+SUMIFS(J6:J1041,$A$6:$A$1041,"i")+SUMIFS(J6:J1041,$A$6:$A$1041,"tx")+SUMIFS(J6:J1041,$A$6:$A$1041,"mf"))-SUMIFS(J6:J1041,$A$6:$A$1041,"noi") -> 0 | ... O3: =(SUMIFS(O6:O1041,$A$6:$A$1041,"r")+SUMIFS(O6:O1041,$A$6:$A$1041,"ll")+SUMIFS(O6:O1041,$A$6:$A$1041,"bd")+SUMIFS(O6:O1041,$A$6:$A$1041,"v")+SUMIFS(O6:O1041,$A$6:$A$1041,"nr")+SUMIFS(O6:O1041,$A$6:$A$1041,"oi")+SUMIFS(O6:O1041,$A$6:$A$1041,"rt")+SUMIFS(O6:O1041,$A$6:$A$1041,"ro")+SUMIFS(O6:O1041,$A$6:$A$1041,"rw"))-(SUMIFS(O6:O1041,$A$6:$A$1041,"ad")+SUMIFS(O6:O1041,$A$6:$A$1041,"m")+SUMIFS(O6:O1041,$A$6:$A$1041,"cs")+SUMIFS(O6:O1041,$A$6:$A$1041,"rm")+SUMIFS(O6:O1041,$A$6:$A$1041,"pr")+SUMIFS(O6:O1041,$A$6:$A$1041,"e")+SUMIFS(O6:O1041,$A$6:$A$1041,"w")+SUMIFS(O6:O1041,$A$6:$A$1041,"o")+SUMIFS(O6:O1041,$A$6:$A$1041,"tr")+SUMIFS(O6:O1041,$A$6:$A$1041,"i")+SUMIFS(O6:O1041,$A$6:$A$1041,"tx")+SUMIFS(O6:O1041,$A$6:$A$1041,"mf"))-SUMIFS(O6:O1041,$A$6:$A$1041,"noi") -> 0
A4: code | B4: category | C4: date1 | D4: date2 | E4: date3 | F4: date4 | G4: date5 | H4: date6 | I4: date7 | J4: date8 | K4: date9 | L4: date10 | M4: date11 | N4: date12 | O4: total
A5: date | B5: Account | C5: 45809 | D5: 45839 | E5: 45870 | F5: 45901 | G5: 45931 | H5: 45962 | I5: 45992 | J5: 46023 | K5: 46054 | L5: 46082 | M5: 46113 | N5: 46143 | O5: Total | Q5: <-- paste data into here
B6: Revenue
B7: Gross Potential Rent
A8: r | B8: 4100100 Apartment Income | C8: 98319 | D8: 98319 | E8: 98319 | F8: 98319 | G8: 98319 | H8: 98319 | I8: 98319 | J8: 98319 | K8: 98319 | L8: 98319 | M8: 98319 | N8: 98319 | O8: 1179828
A9: ll | B9: 4100101 Gain/Loss to Lease | C9: -7470 | D9: -5694 | E9: -4199 | F9: -3850 | G9: -4278 | H9: -4164 | I9: -4094 | J9: -5332 | K9: -3695 | L9: -3174 | M9: -3385 | N9: -3248 | O9: -52583
B10: Total Potential Rent | C10: 90849 | D10: 92625 | E10: 94120 | F10: 94469 | G10: 94041 | H10: 94155 | I10: 94225 | J10: 92987 | K10: 94624 | L10: 95145 | M10: 94934 | N10: 95071 | O10: 1127245
B11: Apartment Rental Adjustments
A12: v | B12: 4100105 Model Units | C12: 0 | D12: 0 | E12: 0 | F12: 0 | G12: 0 | H12: 0 | I12: 0 | J12: 0 | K12: 0 | L12: 0 | M12: -1.83 | N12: -5 | O12: -6.83
A13: nr | B13: 4100106 Vacancy Loss | C13: -13725.89 | D13: -14532.17 | E13: -25005.29 | F13: -18833.49 | G13: -7135.31 | H13: -3387.5 | I13: -2806.89 | J13: -105.42 | K13: -1181.42 | L13: -2687.1 | M13: -3492.74 | N13: -2583 | O13: -95476.22
A14: nr | B14: 4100107 Concessions | C14: 0 | D14: 0 | E14: 0 | F14: 0 | G14: -99.86 | H14: 0 | I14: 0 | J14: 0 | K14: 0 | L14: 0 | M14: 0 | N14: 0 | O14: -99.86
A15: bd | B15: 4100112 Net Prepaids | C15: 732.09 | D15: 5.94 | E15: -2385.74 | F15: 789.69 | G15: 1159.41 | H15: -2248.45 | I15: 960.86 | J15: 64.26 | K15: -1337.56 | L15: -133.27 | M15: 865.34 | N15: -785.12 | O15: -2312.55
A16: bd | B16: 4100113 Net Delinquency | C16: -7210.84 | D16: -15776.46 | E16: -13010.57 | F16: 1307.36 | G16: -4534.37 | H16: 2586.83 | I16: -1844.19 | J16: -1177.15 | K16: 428.94 | L16: -1032.18 | M16: 66.59 | N16: -368.77 | O16: -40564.81
B17: Total Apartment Rental Adjustments | C17: -20204.64 | D17: -30302.69 | E17: -40401.6 | F17: -16736.44 | G17: -10610.13 | H17: -3049.12 | I17: -3690.22 | J17: -1218.31 | K17: -2090.04 | L17: -3852.55 | M17: -2562.64 | N17: -3741.89 | O17: -138460.27
B18: Total Rental Income | C18: 70644.36 | D18: 62322.31 | E18: 53718.4 | F18: 77732.56 | G18: 83430.87 | H18: 91105.88 | I18: 90534.78 | J18: 91768.69 | K18: 92533.96 | L18: 91292.45 | M18: 92371.36 | N18: 91329.11 | O18: 988784.73
A19: oi | B19: Other Income
A20: oi | B20: 4100200 Month to Month | C20: 0 | D20: 0 | E20: 0 | F20: 0 | G20: 135.89 | H20: 400 | I20: 0 | J20: 0 | K20: 0 | L20: 0 | M20: 0 | N20: 0 | O20: 535.89
A21: oi | B21: 4100600 Cleaning fee/Damage Fee | C21: 0 | D21: 0 | E21: 28.7 | F21: 0 | G21: 0 | H21: 0 | I21: 0 | J21: 0 | K21: 0 | L21: 0 | M21: 0 | N21: 0 | O21: 28.7
A22: oi | B22: 4100700 Carport Parking | C22: 105 | D22: 210 | E22: 105 | F22: 141.17 | G22: 210 | H22: 148.17 | I22: 210 | J22: 175 | K22: 140 | L22: 175 | M22: 175 | N22: 175 | O22: 1969.34
A23: oi | B23: 4100800 Pet Fee | C23: 180 | D23: 180 | E23: 135 | F23: 190 | G23: 145.2 | H23: 120 | I23: 120 | J23: 120 | K23: 145 | L23: 160 | M23: 160 | N23: 185 | O23: 1840.2
A24: oi | B24: 4100900 Deposit Forfeiture | C24: 0 | D24: 4500 | E24: 3499 | F24: 350 | G24: 0 | H24: 0 | I24: 0 | J24: 2440 | K24: 0 | L24: 0 | M24: 404.5 | N24: 718.22 | O24: 11911.72
A25: oi | B25: 4101100 Late Charges | C25: 582 | D25: 339.07 | E25: 64.77 | F25: 949.5 | G25: 410 | H25: 1474 | I25: 969 | J25: 1003.8 | K25: 863.5 | L25: 1166.4 | M25: 104.9 | N25: 629.5 | O25: 8556.44
A26: oi | B26: 4101200 NSF Charges | C26: 50 | D26: 0 | E26: 7 | F26: 93 | G26: 0 | H26: 0 | I26: 100 | J26: 200 | K26: 150 | L26: 50 | M26: 50 | N26: 0 | O26: 700
A27: oi | B27: 4101400 Application Fees | C27: 400 | D27: 390 | E27: 149 | F27: 1347 | G27: 660 | H27: 0 | I27: 75 | J27: 0 | K27: 0 | L27: 225 | M27: 375 | N27: 100 | O27: 3721
A28: oi | B28: 4101500 Washer/Dryer Income | C28: 376.07 | D28: 480 | E28: 318.23 | F28: 952.5 | G28: 1135.2 | H28: 1813.87 | I28: 1627.41 | J28: 1850.61 | K28: 1627.42 | L28: 1600.97 | M28: 1633.17 | N28: 1786.45 | O28: 15201.9
A29: oi | B29: 4101600 Administrative Fee | C29: 420 | D29: 0 | E29: 149 | F29: 637 | G29: 400 | H29: 0 | I29: 0 | J29: 110 | K29: 10 | L29: 110 | M29: 300 | N29: -95 | O29: 2041
A30: rw | B30: 4101800 Water Reimbursement | C30: 0 | D30: 0 | E30: 0 | F30: 0 | G30: 2670 | H30: 4240 | I30: 4151 | J30: 0 | K30: 0 | L30: 0 | M30: 0 | N30: 0 | O30: 11061
A31: rt | B31: 4101830 Trash Reimbursement | C31: 1148.04 | D31: 1127.42 | E31: 818.24 | F31: 919.17 | G31: 760.65 | H31: 705.83 | I31: 760 | J31: 0 | K31: 0 | L31: 0 | M31: 0 | N31: 0 | O31: 6239.35
... A36: oi | B36: 4109000 Amenity Fee | C36: 695 | D36: 730 | E36: 626.96 | F36: 1074.61 | G36: 1002.9 | H36: 1128.34 | I36: 1080 | J36: 1050 | K36: 1085 | L36: 1040 | M36: 1035.68 | N36: 1015 | O36: 11563.49
B37: Total Other Income | C37: 4240.11 | D37: 8332.94 | E37: 6362.21 | F37: 7583.38 | G37: 8683.97 | H37: 11569.14 | I37: 10519.99 | J37: 15122.03 | K37: 12237.13 | L37: 12513.32 | M37: 11116.74 | N37: 11380.13 | O37: 119661.09
A38: rev | B38: Total Revenue | C38: 74884.47 | D38: 70655.25 | E38: 60080.61 | F38: 85315.94 | G38: 92114.84 | H38: 102675.02 | I38: 101054.77 | J38: 106890.72 | K38: 104771.09 | L38: 103805.77 | M38: 103488.1 | N38: 102709.24 | O38: 1108445.8
B39: Operating Expenses
B40: Payroll and Benefits
A41: pr | B41: 5100100 Managers and Assistants | C41: 1341.2 | D41: 1152.2 | E41: 4463.55 | F41: 3231.2 | G41: 3735.21 | H41: 3939.96 | I41: 3627.58 | J41: 5111.93 | K41: 3638.08 | L41: 4464.96 | M41: 3900.58 | N41: 2535.58 | O41: 41142.03
A42: pr | B42: 5100200 Leasing | C42: 0 | D42: 0 | E42: 0 | F42: 0 | G42: 0 | H42: 1277.72 | I42: 0 | J42: 0 | K42: 0 | L42: 0 | M42: 0 | N42: 0 | O42: 1277.72
A43: pr | B43: 5100600 General Maintenance Salaries | C43: 0 | D43: 769.45 | E43: 454.35 | F43: 1214.27 | G43: 214.5 | H43: 3322.8 | I43: 1238.45 | J43: 0 | K43: 390 | L43: 2930.13 | M43: 0 | N43: 1733.56 | O43: 12267.51
A44: pr | B44: 5100900 Incentives | C44: 0 | D44: 400 | E44: 0 | F44: 1800 | G44: 1100 | H44: 600 | I44: 300 | J44: 0 | K44: 480 | L44: 1080 | M44: 120 | N44: 135 | O44: 6015
A45: pr | B45: 5280000 Payroll Taxes | C45: 153.51 | D45: 178.7 | E45: 350.5 | F45: 423.56 | G45: 380.46 | H45: 341.75 | I45: 271.95 | J45: 666.79 | K45: 520.01 | L45: 435.68 | M45: 300.16 | N45: 200.95 | O45: 4224.02
A46: pr | B46: 5280100 Workers Compensation | C46: 23.36 | D46: 2.14 | E46: 2.48 | F46: 7.11 | G46: 27.14 | H46: 14.83 | I46: 7.24 | J46: 5.79 | K46: 4.76 | L46: 19.42 | M46: 18.13 | N46: 9.49 | O46: 141.89
B47: Total Payroll and Benefits | C47: 1518.07 | D47: 2502.49 | E47: 5270.88 | F47: 6676.14 | G47: 5457.31 | H47: 9497.06 | I47: 5445.22 | J47: 5784.51 | K47: 5032.85 | L47: 8930.19 | M47: 4338.87 | N47: 4614.58 | O47: 65068.17
B48: Administrative Expenses
A49: ad | B49: 5400100 Office Supplies/General | C49: 10.8 | D49: 55.04 | E49: 263.47 | F49: 14.6 | G49: 638.36 | H49: 34.77 | I49: 16.9 | J49: 217.3 | K49: 9.46 | L49: 9.6 | M49: 315.18 | N49: 10 | O49: 1595.48
A50: ad | B50: 5400200 Postage | C50: 0 | D50: 34.12 | E50: 90.12 | F50: 8.76 | G50: 23.68 | H50: 56.94 | I50: 28.57 | J50: 21.5 | K50: 42.99 | L50: 25.07 | M50: 64.13 | N50: 60.83 | O50: 456.71
A51: ad | B51: 5400900 Auto and Travel | C51: 148.74 | D51: 0 | E51: 200 | F51: 385 | G51: 1027.6 | H51: 0 | I51: 0 | J51: 189 | K51: 0 | L51: 837.2 | M51: 249.98 | N51: 0 | O51: 3037.52
A52: ad | B52: 5401000 Dues and Subscription | C52: 55.36 | D52: 0 | E52: 0 | F52: 134.56 | G52: 0 | H52: 0 | I52: 0 | J52: 0 | K52: 0 | L52: 796.31 | M52: 1592.6 | N52: 0 | O52: 2578.83
A53: ad | B53: 5401200 Application Screening | C53: 93.36 | D53: 93.36 | E53: 93.36 | F53: 93.36 | G53: 93.36 | H53: 93.36 | I53: 0 | J53: 6.81 | K53: 0 | L53: 3.2 | M53: 30.44 | N53: 30.44 | O53: 631.05
A54: ad | B54: 5401300 Legal and Professional | C54: 0 | D54: 2482.98 | E54: 0 | F54: 0 | G54: 0 | H54: 0 | I54: 1696.25 | J54: 0 | K54: 0 | L54: 0 | M54: 0 | N54: 0 | O54: 4179.23
A55: ad | B55: 5401400 Evictions | C55: 200 | D55: 188.95 | E55: 0 | F55: 0 | G55: 0 | H55: 0 | I55: 154.22 | J55: 0 | K55: 0 | L55: 0 | M55: 0 | N55: 0 | O55: 543.17
A56: ad | B56: 5401700 Computer Fees/Permits | C56: 728.9 | D56: 27.76 | E56: 904.74 | F56: 872.29 | G56: 223.25 | H56: 101.27 | I56: 218.67 | J56: 2043.21 | K56: 190.01 | L56: 128.95 | M56: 721.66 | N56: 755.99 | O56: 6916.7
A57: ad | B57: 5401900 Bank Charges | C57: 164.7 | D57: 195.23 | E57: 184.09 | F57: 164.41 | G57: 234.88 | H57: 158.2 | I57: 130.54 | J57: 137.27 | K57: 186.47 | L57: 188.54 | M57: 142.34 | N57: 106.75 | O57: 1993.42
A58: ad | B58: 5402000 Employee Relations | C58: 26.52 | D58: 0 | E58: 230.17 | F58: 226.67 | G58: 0 | H58: 0 | I58: 475 | J58: 0 | K58: 0 | L58: 0 | M58: 0 | N58: 0 | O58: 958.36
B59: Total Administrative Expenses | C59: 1428.38 | D59: 3077.44 | E59: 1965.95 | F59: 1899.65 | G59: 2241.13 | H59: 444.54 | I59: 2720.15 | J59: 2615.09 | K59: 428.93 | L59: 1988.87 | M59: 3116.33 | N59: 964.01 | O59: 22890.47
B60: Contract Services
A61: cs | B61: 5500200 Equipment Rental and Expense | C61: 0 | D61: 0 | E61: 0 | F61: 0 | G61: 0 | H61: 0 | I61: 1604.27 | J61: 0 | K61: 0 | L61: 0 | M61: 0 | N61: 392 | O61: 1996.27
A62: cs | B62: 5500300 Landscaping | C62: 811.88 | D62: 811.88 | E62: 811.88 | F62: 811.88 | G62: 811.88 | H62: 811.88 | I62: 811.88 | J62: 811.88 | K62: 811.88 | L62: 811.88 | M62: 811.88 | N62: 811.88 | O62: 9742.56
A63: cs | B63: 5500350 Landscaping Seasonal | C63: 0 | D63: 0 | E63: 447.55 | F63: 0 | G63: 0 | H63: 0 | I63: 0 | J63: 0 | K63: 0 | L63: 0 | M63: 0 | N63: 0 | O63: 447.55
A64: cs | B64: 5500700 Pest Control | C64: 0 | D64: 0 | E64: 107.98 | F64: 0 | G64: 363.97 | H64: 107.98 | I64: 107.98 | J64: 118.78 | K64: 0 | L64: 237.56 | M64: 0 | N64: 237.56 | O64: 1281.81
A65: cs | B65: 5500800 Alarm Monitoring | C65: 0 | D65: 0 | E65: 0 | F65: 0 | G65: 0 | H65: 0 | I65: 584.56 | J65: 0 | K65: 681.99 | L65: 2432.06 | M65: 0 | N65: 1694.8 | O65: 5393.41
A66: cs | B66: 5500900 Washer/Dryer Expense | C66: 1203.2 | D66: 1203.2 | E66: 1203.21 | F66: 4690.54 | G66: 0 | H66: 2063.27 | I66: 0 | J66: 1806.42 | K66: 0 | L66: 1815.35 | M66: 3761.86 | N66: 0 | O66: 17747.05
B67: Total Contract Services | C67: 2015.08 | D67: 2015.08 | E67: 2570.62 | F67: 5502.42 | G67: 1175.85 | H67: 2983.13 | I67: 3108.69 | J67: 2737.08 | K67: 1493.87 | L67: 5296.85 | M67: 4573.74 | N67: 3136.24 | O67: 36608.65
B68: Marketing
A69: m | B69: 5600200 Advertising Media | C69: 0 | D69: 0 | E69: 0 | F69: 1377.78 | G69: 908 | H69: 0 | I69: 0 | J69: 0 | K69: 1816 | L69: 0 | M69: 908 | N69: 454 | O69: 5463.78
A70: m | B70: 5600500 Mini Model | C70: 0 | D70: 0 | E70: 0 | F70: 141.25 | G70: 0 | H70: 0 | I70: 0 | J70: 0 | K70: 0 | L70: 0 | M70: 0 | N70: 0 | O70: 141.25
A71: m | B71: 5600900 Signs and Banners | C71: 0 | D71: 998.08 | E71: 0 | F71: 0 | G71: 0 | H71: 0 | I71: 0 | J71: 0 | K71: 0 | L71: 0 | M71: 0 | N71: 0 | O71: 998.08
A72: m | B72: 5610400 Resident Relations | C72: 0 | D72: 0 | E72: 127.55 | F72: 0 | G72: 138.5 | H72: 0 | I72: 0 | J72: 0 | K72: 250 | L72: 0 | M72: 0 | N72: 0 | O72: 516.05
A73: m | B73: 5610600 Marketing Materials | C73: 0 | D73: 473.05 | E73: 127.55 | F73: 0 | G73: 37.49 | H73: 0 | I73: 0 | J73: 0 | K73: 0 | L73: 0 | M73: 0 | N73: 0 | O73: 638.09
B74: Total Marketing | C74: 0 | D74: 1471.13 | E74: 255.1 | F74: 1519.03 | G74: 1083.99 | H74: 0 | I74: 0 | J74: 0 | K74: 2066 | L74: 0 | M74: 908 | N74: 454 | O74: 7757.25
B75: Maintenance and Repairs
A76: rm | B76: 5700100 Carpentry | C76: 0 | D76: 21.62 | E76: 0 | F76: 0 | G76: 0 | H76: 0 | I76: 0 | J76: 0 | K76: 0 | L76: 0 | M76: 0 | N76: -32.12 | O76: -10.5
A77: rm | B77: 5700200 Paint Contract | C77: 1828.3 | D77: 5574.56 | E77: 1910 | F77: 3200.6 | G77: 9664.62 | H77: 2274.8 | I77: 0 | J77: 443.83 | K77: 33.53 | L77: 1010.8 | M77: 2716 | N77: 1377.4 | O77: 30034.44
A78: rm | B78: 5700500 Small Tools | C78: 0 | D78: 260.68 | E78: 0 | F78: 359.23 | G78: 23.71 | H78: 0 | I78: 0 | J78: 0 | K78: 0 | L78: 0 | M78: 0 | N78: 0 | O78: 643.62
A79: rm | B79: 5700700 Electrical Parts and Labor | C79: 63.36 | D79: 92.88 | E79: 0 | F79: 25.94 | G79: 154.66 | H79: 103.4 | I79: 0 | J79: 0 | K79: 94.77 | L79: 12.59 | M79: 0 | N79: 0 | O79: 547.6
A80: rm | B80: 5700900 Air Conditioning and Heat | C80: 0 | D80: 350.02 | E80: 0 | F80: 165.75 | G80: 1213.2 | H80: 283.9 | I80: 496.71 | J80: 583.31 | K80: 158.23 | L80: 1544.37 | M80: 51.96 | N80: 0 | O80: 4847.45
A81: rm | B81: 5701000 Pool Supplies and Repairs | C81: 0 | D81: 180.03 | E81: 0 | F81: 558.27 | G81: 538.9 | H81: 270.62 | I81: 299.13 | J81: 0 | K81: 15.99 | L81: 249.23 | M81: 0 | N81: 968.99 | O81: 3081.16
A82: rm | B82: 5701100 General Supplies | C82: 0 | D82: 0 | E82: 0 | F82: 0 | G82: 0 | H82: 0 | I82: 0 | J82: 0 | K82: 626.6 | L82: 0 | M82: 0 | N82: 0 | O82: 626.6
A83: rm | B83: 5701200 Landscaping Supplies | C83: 0 | D83: 0 | E83: 0 | F83: 351.38 | G83: 10.29 | H83: 0 | I83: 0 | J83: 0 | K83: 0 | L83: 0 | M83: 0 | N83: 0 | O83: 361.67
A84: rm | B84: 5701300 Plumbing Labor and Parts | C84: 72.53 | D84: 767.46 | E84: 0 | F84: 638.51 | G84: -57.85 | H84: 179.37 | I84: 0 | J84: 0 | K84: 240.17 | L84: 467.66 | M84: 45.45 | N84: 0 | O84: 2353.3
A85: rm | B85: 5701600 Glass and Mirror | C85: 0 | D85: 0 | E85: 0 | F85: 0 | G85: 0 | H85: 0 | I85: 0 | J85: 0 | K85: 708.36 | L85: 0 | M85: 0 | N85: 0 | O85: 708.36
A86: rm | B86: 5701700 Driveway and Sidewalk Repairs | C86: 0 | D86: 0 | E86: 0 | F86: 110.22 | G86: 0 | H86: 0 | I86: 0 | J86: 0 | K86: 0 | L86: 0 | M86: 0 | N86: 0 | O86: 110.22
A87: rm | B87: 5701800 Appliance | C87: 672.8 | D87: 483.61 | E87: 0 | F87: 402 | G87: 361.15 | H87: 78.18 | I87: 0 | J87: 0 | K87: 619.35 | L87: 416.09 | M87: 125.12 | N87: 419.02 | O87: 3577.32
... A95: rm | B95: 5709901 Vendor Rebate | C95: 0 | D95: 0 | E95: 0 | F95: 0 | G95: 0 | H95: -88.57 | I95: 0 | J95: 0 | K95: -830.06 | L95: 0 | M95: 0 | N95: -95.17 | O95: -1013.8
B96: Total Maintenance and Repairs | C96: 3572.38 | D96: 9335.98 | E96: 3785.42 | F96: 8133.94 | G96: 13008.47 | H96: 8266.34 | I96: 1379.39 | J96: 1027.14 | K96: 2241.62 | L96: 3818.48 | M96: 4448.39 | N96: 3252.88 | O96: 62270.43
B97: Turnover Costs
B98: Utilities
A99: e | B99: 5800100 Electricity | C99: 618.3 | D99: 552.71 | E99: 638.36 | F99: 347.37 | G99: 648.03 | H99: 582.23 | I99: 513.13 | J99: 648.6 | K99: 622.88 | L99: 522.52 | M99: 517.48 | N99: 673.93 | O99: 6885.54
A100: e | B100: 5800101 Electricity - Vacant | C100: 579.94 | D100: 830.21 | E100: 962.24 | F100: 1640.88 | G100: 866.55 | H100: 1067.5 | I100: 512.09 | J100: 196.11 | K100: -858.19 | L100: 422.7 | M100: 261.8 | N100: 241.75 | O100: 6723.58
A101: w | B101: 5800300 Water | C101: 6843.75 | D101: 5492.7 | E101: 5674.43 | F101: 5635.35 | G101: 6209.14 | H101: 5149.47 | I101: 5405.45 | J101: 5337.29 | K101: 5551.64 | L101: 5448.33 | M101: 5432.76 | N101: 5831.32 | O101: 68011.63
A102: tr | B102: 5800400 Trash Removal | C102: 0 | D102: 1518 | E102: 2418 | F102: 1518 | G102: 2440.55 | H102: 1518 | I102: 1624.2 | J102: 1624.2 | K102: 2629.26 | L102: 1624.2 | M102: 1624 | N102: 1624.2 | O102: 20162.61
A103: tr | B103: 5800401 Valet Trash | C103: 856.6 | D103: 2550.79 | E103: 0 | F103: 772.55 | G103: 772.55 | H103: 918.53 | I103: 918.53 | J103: 263.47 | K103: 830.06 | L103: 200 | M103: 1080.06 | N103: 968.53 | O103: 10131.67
A104: o | B104: 5800500 Telephone | C104: 100.28 | D104: 73.87 | E104: 73.63 | F104: 59.92 | G104: 60.28 | H104: 480.09 | I104: 60.34 | J104: 60.34 | K104: 60.33 | L104: 60.33 | M104: 60.33 | N104: 280.79 | O104: 1430.53
B105: Total Utilities | C105: 8998.87 | D105: 11018.28 | E105: 9766.66 | F105: 9974.07 | G105: 10997.1 | H105: 9715.82 | I105: 9033.74 | J105: 8130.01 | K105: 8835.98 | L105: 8278.08 | M105: 8976.43 | N105: 9620.52 | O105: 113345.56
B106: Management Fees
A107: mf | B107: 5900100 Management Fees | C107: 2995.38 | D107: 2826.21 | E107: 2403.22 | F107: 3412.64 | G107: 3684.59 | H107: 4107 | I107: 4022.19 | J107: 4275.63 | K107: 4190.84 | L107: 4152.23 | M107: 4019.53 | N107: 4028.37 | O107: 44117.83
B108: Total Management Fees | C108: 2995.38 | D108: 2826.21 | E108: 2403.22 | F108: 3412.64 | G108: 3684.59 | H108: 4107 | I108: 4022.19 | J108: 4275.63 | K108: 4190.84 | L108: 4152.23 | M108: 4019.53 | N108: 4028.37 | O108: 44117.83
B109: Taxes
A110: tx | B110: 6200100 Property Taxes | C110: 7867.13 | D110: 7867.13 | E110: 7867.13 | F110: 7867.13 | G110: 7867.13 | H110: 7867.13 | I110: 21857.1 | J110: 9033 | K110: 9033 | L110: 9033 | M110: 9033 | N110: 9033 | O110: 114224.88
B111: Total Taxes | C111: 7867.13 | D111: 7867.13 | E111: 7867.13 | F111: 7867.13 | G111: 7867.13 | H111: 7867.13 | I111: 21857.1 | J111: 9033 | K111: 9033 | L111: 9033 | M111: 9033 | N111: 9033 | O111: 114224.88
...

Sheet masterkeytable
A1: code | B1: category | C1: date1 | D1: date2 | E1: date3 | F1: date4 | G1: date5 | H1: date6 | I1: date7 | J1: date8 | K1: date9 | L1: date10 | M1: date11 | N1: date12 | O1: total
B2: Income
A3: r | B3: Rental Income
A4: ll | B4: (Loss to Lease) / Gain to Lease
A5: v | B5: Vacancy
A6: nr | B6: Non-Revenue/Concessions
A7: bd | B7: Bad Debt
A8: rw | B8: RUBS - Water/Sewer
A9: ro | B9: RUBS - Electric/Gas/Other
A10: oi | B10: Other Income
A11: rev | B11: Total Income
B13: Expense
A14: cs | B14: Contract Services
A15: rm | B15: Repair & Maintenance
A16: ad | B16: Administrative
A17: m | B17: Marketing
A18: pr | B18: Payroll
A19: w | B19: Water/Sewer
A20: tr | B20: Trash
A21: e | B21: Electric
A22: o | B22: Gas/Other
A23: mf | B23: Management Fee
A24: i | B24: Insurance
A25: tx | B25: Real Estate Taxes
... A28: noi | B28: Net Operating Income

Sheet Masterkey
B1: Income
A2: r | B2: Rental Income
A3: ll | B3: (Loss to Lease) / Gain to Lease
A4: v | B4: Vacancy
A5: nr | B5: Non-Revenue/Concessions
A6: bd | B6: Bad Debt
A7: rw | B7: RUBS - Water/Sewer
A8: ro | B8: RUBS - Electric/Gas/Other
A9: oi | B9: Other Income
A10: rev | B10: Total Income
B12: Expense
A13: cs | B13: Contract Services
A14: rm | B14: Repair & Maintenance
A15: ad | B15: Administrative
A16: m | B16: Marketing
A17: pr | B17: Payroll
A18: w | B18: Water/Sewer
A19: tr | B19: Trash
A20: e | B20: Electric
A21: o | B21: Gas/Other
A22: mf | B22: Management Fee
A23: i | B23: Insurance
A24: tx | B24: Real Estate Taxes
... A27: noi | B27: Net Operating Income

Sheet Final T-12
A1: code | B1: category | C1: date1 | D1: date2 | E1: date3 | F1: date4 | G1: date5 | H1: date6 | I1: date7 | J1: date8 | K1: date9 | L1: date10 | M1: date11 | N1: date12 | O1: total
A2: date | B2: Account | C2: 45809 | D2: 45839 | E2: 45870 | F2: 45901 | G2: 45931 | H2: 45962 | I2: 45992 | J2: 46023 | K2: 46054 | L2: 46082 | M2: 46113 | N2: 46143 | O2: Total
A4: r | B4: Rental Income
A5: r | B5: 4100100 Apartment Income | C5: 98319 | D5: 98319 | E5: 98319 | F5: 98319 | G5: 98319 | H5: 98319 | I5: 98319 | J5: 98319 | K5: 98319 | L5: 98319 | M5: 98319 | N5: 98319 | O5: 1179828
A6: ll | B6: (Loss to Lease) / Gain to Lease
A7: ll | B7: 4100101 Gain/Loss to Lease | C7: -7470 | D7: -5694 | E7: -4199 | F7: -3850 | G7: -4278 | H7: -4164 | I7: -4094 | J7: -5332 | K7: -3695 | L7: -3174 | M7: -3385 | N7: -3248 | O7: -52583
A8: v | B8: Vacancy
A9: v | B9: 4100105 Model Units | C9: 0 | D9: 0 | E9: 0 | F9: 0 | G9: 0 | H9: 0 | I9: 0 | J9: 0 | K9: 0 | L9: 0 | M9: -1.83 | N9: -5 | O9: -6.83
A10: nr | B10: Non-Revenue/Concessions
A11: nr | B11: 4100106 Vacancy Loss | C11: -13725.89 | D11: -14532.17 | E11: -25005.29 | F11: -18833.49 | G11: -7135.31 | H11: -3387.5 | I11: -2806.89 | J11: -105.42 | K11: -1181.42 | L11: -2687.1 | M11: -3492.74 | N11: -2583 | O11: -95476.22
A12: nr | B12: 4100107 Concessions | C12: 0 | D12: 0 | E12: 0 | F12: 0 | G12: -99.86 | H12: 0 | I12: 0 | J12: 0 | K12: 0 | L12: 0 | M12: 0 | N12: 0 | O12: -99.86
A13: bd | B13: Bad Debt
A14: bd | B14: 4100112 Net Prepaids | C14: 732.09 | D14: 5.94 | E14: -2385.74 | F14: 789.69 | G14: 1159.41 | H14: -2248.45 | I14: 960.86 | J14: 64.26 | K14: -1337.56 | L14: -133.27 | M14: 865.34 | N14: -785.12 | O14: -2312.55
A15: bd | B15: 4100113 Net Delinquency | C15: -7210.84 | D15: -15776.46 | E15: -13010.57 | F15: 1307.36 | G15: -4534.37 | H15: 2586.83 | I15: -1844.19 | J15: -1177.15 | K15: 428.94 | L15: -1032.18 | M15: 66.59 | N15: -368.77 | O15: -40564.81
A16: rw | B16: RUBS - Water/Sewer
A17: rw | B17: 4101800 Water Reimbursement | C17: 0 | D17: 0 | E17: 0 | F17: 0 | G17: 2670 | H17: 4240 | I17: 4151 | J17: 0 | K17: 0 | L17: 0 | M17: 0 | N17: 0 | O17: 11061
A18: ro | B18: RUBS - Electric/Gas/Other
A19: rt | B19: 4101830 Trash Reimbursement | C19: 1148.04 | D19: 1127.42 | E19: 818.24 | F19: 919.17 | G19: 760.65 | H19: 705.83 | I19: 760 | J19: 0 | K19: 0 | L19: 0 | M19: 0 | N19: 0 | O19: 6239.35
A20: oi | B20: Other Income
A21: oi | B21: Other Income | C21: 0 | D21: 0 | E21: 0 | F21: 0 | G21: 0 | H21: 0 | I21: 0 | J21: 0 | K21: 0 | L21: 0 | M21: 0 | N21: 0 | O21: 0
A22: oi | B22: 4100200 Month to Month | C22: 0 | D22: 0 | E22: 0 | F22: 0 | G22: 135.89 | H22: 400 | I22: 0 | J22: 0 | K22: 0 | L22: 0 | M22: 0 | N22: 0 | O22: 535.89
A23: oi | B23: 4100600 Cleaning fee/Damage Fee | C23: 0 | D23: 0 | E23: 28.7 | F23: 0 | G23: 0 | H23: 0 | I23: 0 | J23: 0 | K23: 0 | L23: 0 | M23: 0 | N23: 0 | O23: 28.7
A24: oi | B24: 4100700 Carport Parking | C24: 105 | D24: 210 | E24: 105 | F24: 141.17 | G24: 210 | H24: 148.17 | I24: 210 | J24: 175 | K24: 140 | L24: 175 | M24: 175 | N24: 175 | O24: 1969.34
A25: oi | B25: 4100800 Pet Fee | C25: 180 | D25: 180 | E25: 135 | F25: 190 | G25: 145.2 | H25: 120 | I25: 120 | J25: 120 | K25: 145 | L25: 160 | M25: 160 | N25: 185 | O25: 1840.2
A26: oi | B26: 4100900 Deposit Forfeiture | C26: 0 | D26: 4500 | E26: 3499 | F26: 350 | G26: 0 | H26: 0 | I26: 0 | J26: 2440 | K26: 0 | L26: 0 | M26: 404.5 | N26: 718.22 | O26: 11911.72
A27: oi | B27: 4101100 Late Charges | C27: 582 | D27: 339.07 | E27: 64.77 | F27: 949.5 | G27: 410 | H27: 1474 | I27: 969 | J27: 1003.8 | K27: 863.5 | L27: 1166.4 | M27: 104.9 | N27: 629.5 | O27: 8556.44
A28: oi | B28: 4101200 NSF Charges | C28: 50 | D28: 0 | E28: 7 | F28: 93 | G28: 0 | H28: 0 | I28: 100 | J28: 200 | K28: 150 | L28: 50 | M28: 50 | N28: 0 | O28: 700
A29: oi | B29: 4101400 Application Fees | C29: 400 | D29: 390 | E29: 149 | F29: 1347 | G29: 660 | H29: 0 | I29: 75 | J29: 0 | K29: 0 | L29: 225 | M29: 375 | N29: 100 | O29: 3721
A30: oi | B30: 4101500 Washer/Dryer Income | C30: 376.07 | D30: 480 | E30: 318.23 | F30: 952.5 | G30: 1135.2 | H30: 1813.87 | I30: 1627.41 | J30: 1850.61 | K30: 1627.42 | L30: 1600.97 | M30: 1633.17 | N30: 1786.45 | O30: 15201.9
A31: oi | B31: 4101600 Administrative Fee | C31: 420 | D31: 0 | E31: 149 | F31: 637 | G31: 400 | H31: 0 | I31: 0 | J31: 110 | K31: 10 | L31: 110 | M31: 300 | N31: -95 | O31: 2041
A32: oi | B32: 4101835 Valet Trash Reimbursement | C32: 44.84 | D32: 125.97 | E32: 251.61 | F32: 619.77 | G32: 834.89 | H32: 1166.5 | I32: 1060.48 | J32: 0 | K32: 0 | L32: 0 | M32: 0 | N32: 0 | O32: 4104.06
... A37: rev | B37: Total Revenue | C37: 74884.47 | D37: 70655.25 | E37: 60080.61 | F37: 85315.94 | G37: 92114.84 | H37: 102675.02 | I37: 101054.77 | J37: 106890.72 | K37: 104771.09 | L37: 103805.77 | M37: 103488.1 | N37: 102709.24 | O37: 1108445.8
B39: Expense
A40: cs | B40: Contract Services
A41: cs | B41: 5500200 Equipment Rental and Expense | C41: 0 | D41: 0 | E41: 0 | F41: 0 | G41: 0 | H41: 0 | I41: 1604.27 | J41: 0 | K41: 0 | L41: 0 | M41: 0 | N41: 392 | O41: 1996.27
A42: cs | B42: 5500300 Landscaping | C42: 811.88 | D42: 811.88 | E42: 811.88 | F42: 811.88 | G42: 811.88 | H42: 811.88 | I42: 811.88 | J42: 811.88 | K42: 811.88 | L42: 811.88 | M42: 811.88 | N42: 811.88 | O42: 9742.56
A43: cs | B43: 5500350 Landscaping Seasonal | C43: 0 | D43: 0 | E43: 447.55 | F43: 0 | G43: 0 | H43: 0 | I43: 0 | J43: 0 | K43: 0 | L43: 0 | M43: 0 | N43: 0 | O43: 447.55
A44: cs | B44: 5500700 Pest Control | C44: 0 | D44: 0 | E44: 107.98 | F44: 0 | G44: 363.97 | H44: 107.98 | I44: 107.98 | J44: 118.78 | K44: 0 | L44: 237.56 | M44: 0 | N44: 237.56 | O44: 1281.81
A45: cs | B45: 5500800 Alarm Monitoring | C45: 0 | D45: 0 | E45: 0 | F45: 0 | G45: 0 | H45: 0 | I45: 584.56 | J45: 0 | K45: 681.99 | L45: 2432.06 | M45: 0 | N45: 1694.8 | O45: 5393.41
A46: cs | B46: 5500900 Washer/Dryer Expense | C46: 1203.2 | D46: 1203.2 | E46: 1203.21 | F46: 4690.54 | G46: 0 | H46: 2063.27 | I46: 0 | J46: 1806.42 | K46: 0 | L46: 1815.35 | M46: 3761.86 | N46: 0 | O46: 17747.05
A47: rm | B47: Repair & Maintenance
A48: rm | B48: 5700100 Carpentry | C48: 0 | D48: 21.62 | E48: 0 | F48: 0 | G48: 0 | H48: 0 | I48: 0 | J48: 0 | K48: 0 | L48: 0 | M48: 0 | N48: -32.12 | O48: -10.5
A49: rm | B49: 5700200 Paint Contract | C49: 1828.3 | D49: 5574.56 | E49: 1910 | F49: 3200.6 | G49: 9664.62 | H49: 2274.8 | I49: 0 | J49: 443.83 | K49: 33.53 | L49: 1010.8 | M49: 2716 | N49: 1377.4 | O49: 30034.44
A50: rm | B50: 5700500 Small Tools | C50: 0 | D50: 260.68 | E50: 0 | F50: 359.23 | G50: 23.71 | H50: 0 | I50: 0 | J50: 0 | K50: 0 | L50: 0 | M50: 0 | N50: 0 | O50: 643.62
A51: rm | B51: 5700700 Electrical Parts and Labor | C51: 63.36 | D51: 92.88 | E51: 0 | F51: 25.94 | G51: 154.66 | H51: 103.4 | I51: 0 | J51: 0 | K51: 94.77 | L51: 12.59 | M51: 0 | N51: 0 | O51: 547.6
A52: rm | B52: 5700900 Air Conditioning and Heat | C52: 0 | D52: 350.02 | E52: 0 | F52: 165.75 | G52: 1213.2 | H52: 283.9 | I52: 496.71 | J52: 583.31 | K52: 158.23 | L52: 1544.37 | M52: 51.96 | N52: 0 | O52: 4847.45
A53: rm | B53: 5701000 Pool Supplies and Repairs | C53: 0 | D53: 180.03 | E53: 0 | F53: 558.27 | G53: 538.9 | H53: 270.62 | I53: 299.13 | J53: 0 | K53: 15.99 | L53: 249.23 | M53: 0 | N53: 968.99 | O53: 3081.16
A54: rm | B54: 5701100 General Supplies | C54: 0 | D54: 0 | E54: 0 | F54: 0 | G54: 0 | H54: 0 | I54: 0 | J54: 0 | K54: 626.6 | L54: 0 | M54: 0 | N54: 0 | O54: 626.6
A55: rm | B55: 5701200 Landscaping Supplies | C55: 0 | D55: 0 | E55: 0 | F55: 351.38 | G55: 10.29 | H55: 0 | I55: 0 | J55: 0 | K55: 0 | L55: 0 | M55: 0 | N55: 0 | O55: 361.67
A56: rm | B56: 5701300 Plumbing Labor and Parts | C56: 72.53 | D56: 767.46 | E56: 0 | F56: 638.51 | G56: -57.85 | H56: 179.37 | I56: 0 | J56: 0 | K56: 240.17 | L56: 467.66 | M56: 45.45 | N56: 0 | O56: 2353.3
A57: rm | B57: 5701600 Glass and Mirror | C57: 0 | D57: 0 | E57: 0 | F57: 0 | G57: 0 | H57: 0 | I57: 0 | J57: 0 | K57: 708.36 | L57: 0 | M57: 0 | N57: 0 | O57: 708.36
A58: rm | B58: 5701700 Driveway and Sidewalk Repairs | C58: 0 | D58: 0 | E58: 0 | F58: 110.22 | G58: 0 | H58: 0 | I58: 0 | J58: 0 | K58: 0 | L58: 0 | M58: 0 | N58: 0 | O58: 110.22
A59: rm | B59: 5701800 Appliance | C59: 672.8 | D59: 483.61 | E59: 0 | F59: 402 | G59: 361.15 | H59: 78.18 | I59: 0 | J59: 0 | K59: 619.35 | L59: 416.09 | M59: 125.12 | N59: 419.02 | O59: 3577.32
... A67: rm | B67: 5709901 Vendor Rebate | C67: 0 | D67: 0 | E67: 0 | F67: 0 | G67: 0 | H67: -88.57 | I67: 0 | J67: 0 | K67: -830.06 | L67: 0 | M67: 0 | N67: -95.17 | O67: -1013.8
A68: ad | B68: Administrative
A69: ad | B69: 5400100 Office Supplies/General | C69: 10.8 | D69: 55.04 | E69: 263.47 | F69: 14.6 | G69: 638.36 | H69: 34.77 | I69: 16.9 | J69: 217.3 | K69: 9.46 | L69: 9.6 | M69: 315.18 | N69: 10 | O69: 1595.48
A70: ad | B70: 5400200 Postage | C70: 0 | D70: 34.12 | E70: 90.12 | F70: 8.76 | G70: 23.68 | H70: 56.94 | I70: 28.57 | J70: 21.5 | K70: 42.99 | L70: 25.07 | M70: 64.13 | N70: 60.83 | O70: 456.71
A71: ad | B71: 5400900 Auto and Travel | C71: 148.74 | D71: 0 | E71: 200 | F71: 385 | G71: 1027.6 | H71: 0 | I71: 0 | J71: 189 | K71: 0 | L71: 837.2 | M71: 249.98 | N71: 0 | O71: 3037.52
A72: ad | B72: 5401000 Dues and Subscription | C72: 55.36 | D72: 0 | E72: 0 | F72: 134.56 | G72: 0 | H72: 0 | I72: 0 | J72: 0 | K72: 0 | L72: 796.31 | M72: 1592.6 | N72: 0 | O72: 2578.83
A73: ad | B73: 5401200 Application Screening | C73: 93.36 | D73: 93.36 | E73: 93.36 | F73: 93.36 | G73: 93.36 | H73: 93.36 | I73: 0 | J73: 6.81 | K73: 0 | L73: 3.2 | M73: 30.44 | N73: 30.44 | O73: 631.05
A74: ad | B74: 5401300 Legal and Professional | C74: 0 | D74: 2482.98 | E74: 0 | F74: 0 | G74: 0 | H74: 0 | I74: 1696.25 | J74: 0 | K74: 0 | L74: 0 | M74: 0 | N74: 0 | O74: 4179.23
A75: ad | B75: 5401400 Evictions | C75: 200 | D75: 188.95 | E75: 0 | F75: 0 | G75: 0 | H75: 0 | I75: 154.22 | J75: 0 | K75: 0 | L75: 0 | M75: 0 | N75: 0 | O75: 543.17
A76: ad | B76: 5401700 Computer Fees/Permits | C76: 728.9 | D76: 27.76 | E76: 904.74 | F76: 872.29 | G76: 223.25 | H76: 101.27 | I76: 218.67 | J76: 2043.21 | K76: 190.01 | L76: 128.95 | M76: 721.66 | N76: 755.99 | O76: 6916.7
A77: ad | B77: 5401900 Bank Charges | C77: 164.7 | D77: 195.23 | E77: 184.09 | F77: 164.41 | G77: 234.88 | H77: 158.2 | I77: 130.54 | J77: 137.27 | K77: 186.47 | L77: 188.54 | M77: 142.34 | N77: 106.75 | O77: 1993.42
A78: ad | B78: 5402000 Employee Relations | C78: 26.52 | D78: 0 | E78: 230.17 | F78: 226.67 | G78: 0 | H78: 0 | I78: 475 | J78: 0 | K78: 0 | L78: 0 | M78: 0 | N78: 0 | O78: 958.36
A79: m | B79: Marketing
A80: m | B80: 5600200 Advertising Media | C80: 0 | D80: 0 | E80: 0 | F80: 1377.78 | G80: 908 | H80: 0 | I80: 0 | J80: 0 | K80: 1816 | L80: 0 | M80: 908 | N80: 454 | O80: 5463.78
A81: m | B81: 5600500 Mini Model | C81: 0 | D81: 0 | E81: 0 | F81: 141.25 | G81: 0 | H81: 0 | I81: 0 | J81: 0 | K81: 0 | L81: 0 | M81: 0 | N81: 0 | O81: 141.25
A82: m | B82: 5600900 Signs and Banners | C82: 0 | D82: 998.08 | E82: 0 | F82: 0 | G82: 0 | H82: 0 | I82: 0 | J82: 0 | K82: 0 | L82: 0 | M82: 0 | N82: 0 | O82: 998.08
A83: m | B83: 5610400 Resident Relations | C83: 0 | D83: 0 | E83: 127.55 | F83: 0 | G83: 138.5 | H83: 0 | I83: 0 | J83: 0 | K83: 250 | L83: 0 | M83: 0 | N83: 0 | O83: 516.05
A84: m | B84: 5610600 Marketing Materials | C84: 0 | D84: 473.05 | E84: 127.55 | F84: 0 | G84: 37.49 | H84: 0 | I84: 0 | J84: 0 | K84: 0 | L84: 0 | M84: 0 | N84: 0 | O84: 638.09
A85: pr | B85: Payroll
A86: pr | B86: 5100100 Managers and Assistants | C86: 1341.2 | D86: 1152.2 | E86: 4463.55 | F86: 3231.2 | G86: 3735.21 | H86: 3939.96 | I86: 3627.58 | J86: 5111.93 | K86: 3638.08 | L86: 4464.96 | M86: 3900.58 | N86: 2535.58 | O86: 41142.03
A87: pr | B87: 5100200 Leasing | C87: 0 | D87: 0 | E87: 0 | F87: 0 | G87: 0 | H87: 1277.72 | I87: 0 | J87: 0 | K87: 0 | L87: 0 | M87: 0 | N87: 0 | O87: 1277.72
A88: pr | B88: 5100600 General Maintenance Salaries | C88: 0 | D88: 769.45 | E88: 454.35 | F88: 1214.27 | G88: 214.5 | H88: 3322.8 | I88: 1238.45 | J88: 0 | K88: 390 | L88: 2930.13 | M88: 0 | N88: 1733.56 | O88: 12267.51
A89: pr | B89: 5100900 Incentives | C89: 0 | D89: 400 | E89: 0 | F89: 1800 | G89: 1100 | H89: 600 | I89: 300 | J89: 0 | K89: 480 | L89: 1080 | M89: 120 | N89: 135 | O89: 6015
A90: pr | B90: 5280000 Payroll Taxes | C90: 153.51 | D90: 178.7 | E90: 350.5 | F90: 423.56 | G90: 380.46 | H90: 341.75 | I90: 271.95 | J90: 666.79 | K90: 520.01 | L90: 435.68 | M90: 300.16 | N90: 200.95 | O90: 4224.02
A91: pr | B91: 5280100 Workers Compensation | C91: 23.36 | D91: 2.14 | E91: 2.48 | F91: 7.11 | G91: 27.14 | H91: 14.83 | I91: 7.24 | J91: 5.79 | K91: 4.76 | L91: 19.42 | M91: 18.13 | N91: 9.49 | O91: 141.89
A92: w | B92: Water/Sewer
A93: w | B93: 5800300 Water | C93: 6843.75 | D93: 5492.7 | E93: 5674.43 | F93: 5635.35 | G93: 6209.14 | H93: 5149.47 | I93: 5405.45 | J93: 5337.29 | K93: 5551.64 | L93: 5448.33 | M93: 5432.76 | N93: 5831.32 | O93: 68011.63
A94: tr | B94: Trash
A95: tr | B95: 5800400 Trash Removal | C95: 0 | D95: 1518 | E95: 2418 | F95: 1518 | G95: 2440.55 | H95: 1518 | I95: 1624.2 | J95: 1624.2 | K95: 2629.26 | L95: 1624.2 | M95: 1624 | N95: 1624.2 | O95: 20162.61
A96: tr | B96: 5800401 Valet Trash | C96: 856.6 | D96: 2550.79 | E96: 0 | F96: 772.55 | G96: 772.55 | H96: 918.53 | I96: 918.53 | J96: 263.47 | K96: 830.06 | L96: 200 | M96: 1080.06 | N96: 968.53 | O96: 10131.67
A97: e | B97: Electric
A98: e | B98: 5800100 Electricity | C98: 618.3 | D98: 552.71 | E98: 638.36 | F98: 347.37 | G98: 648.03 | H98: 582.23 | I98: 513.13 | J98: 648.6 | K98: 622.88 | L98: 522.52 | M98: 517.48 | N98: 673.93 | O98: 6885.54
A99: e | B99: 5800101 Electricity - Vacant | C99: 579.94 | D99: 830.21 | E99: 962.24 | F99: 1640.88 | G99: 866.55 | H99: 1067.5 | I99: 512.09 | J99: 196.11 | K99: -858.19 | L99: 422.7 | M99: 261.8 | N99: 241.75 | O99: 6723.58
A100: o | B100: Gas/Other
A101: o | B101: 5800500 Telephone | C101: 100.28 | D101: 73.87 | E101: 73.63 | F101: 59.92 | G101: 60.28 | H101: 480.09 | I101: 60.34 | J101: 60.34 | K101: 60.33 | L101: 60.33 | M101: 60.33 | N101: 280.79 | O101: 1430.53
A102: mf | B102: Management Fee
A103: mf | B103: 5900100 Management Fees | C103: 2995.38 | D103: 2826.21 | E103: 2403.22 | F103: 3412.64 | G103: 3684.59 | H103: 4107 | I103: 4022.19 | J103: 4275.63 | K103: 4190.84 | L103: 4152.23 | M103: 4019.53 | N103: 4028.37 | O103: 44117.83
A104: i | B104: Insurance
A105: i | B105: 6300100 Insurance | C105: 0 | D105: 0 | E105: 0 | F105: 0 | G105: 0 | H105: 0 | I105: 0 | J105: 3346.78 | K105: 3346.78 | L105: 3346.78 | M105: 3346.78 | N105: 3346.78 | O105: 16733.9
A106: tx | B106: Real Estate Taxes
A107: tx | B107: 6200100 Property Taxes | C107: 7867.13 | D107: 7867.13 | E107: 7867.13 | F107: 7867.13 | G107: 7867.13 | H107: 7867.13 | I107: 21857.1 | J107: 9033 | K107: 9033 | L107: 9033 | M107: 9033 | N107: 9033 | O107: 114224.88
A108: exp | B108: Total Expense | C108: 28395.29 | D108: 40113.74 | E108: 33884.98 | F108: 44985.02 | G108: 45515.57 | H108: 42881.02 | I108: 47566.48 | J108: 36949.24 | K108: 36669.87 | L108: 44844.48 | M108: 42761.07 | N108: 38450.38 | O108: 483017.14
A110: noi | B110: Net Operating Income | C110: 46489.18 | D110: 30541.51 | E110: 26195.63 | F110: 40330.92 | G110: 46599.27 | H110: 59794 | I110: 53488.29 | J110: 69941.48 | K110: 68101.22 | L110: 58961.29 | M110: 60727.03 | N110: 64258.86 | O110: 625428.68

Sheet codes
A1: Codes
A3: r | B3: rents
A4: ll | B4: loss to lease
A5: v | B5: vacancy
A6: nr | B6: non-revenue/concessions
A7: bd | B7: bad debt
A8: rw | B8: rubs water
A9: rt | B9: rubs trash
A10: ro | B10: rubs other
A11: oi | B11: other income
A12: rev | B12: revenue
A13: cs | B13: contract services
A14: rm | B14: repairs and maintenance
... A26: noi | B26: net operating income

Sheet Trailing 12 Month Statement
A1: code | B1: category | C1: date1 | D1: date2 | E1: date3 | F1: date4 | G1: date5 | H1: date6 | I1: date7 | J1: date8 | K1: date9 | L1: date10 | M1: date11 | N1: date12 | O1: total
A3: r | B3: Rental Income
A4: r | B4: 4100100 Apartment Income | C4: 98319 | D4: 98319 | E4: 98319 | F4: 98319 | G4: 98319 | H4: 98319 | I4: 98319 | J4: 98319 | K4: 98319 | L4: 98319 | M4: 98319 | N4: 98319 | O4: 1179828
A5: ll | B5: (Loss to Lease) / Gain to Lease
A6: ll | B6: 4100101 Gain/Loss to Lease | C6: -7470 | D6: -5694 | E6: -4199 | F6: -3850 | G6: -4278 | H6: -4164 | I6: -4094 | J6: -5332 | K6: -3695 | L6: -3174 | M6: -3385 | N6: -3248 | O6: -52583
A7: v | B7: Vacancy
A8: v | B8: 4100105 Model Units | C8: 0 | D8: 0 | E8: 0 | F8: 0 | G8: 0 | H8: 0 | I8: 0 | J8: 0 | K8: 0 | L8: 0 | M8: -1.83 | N8: -5 | O8: -6.83
A9: nr | B9: Non-Revenue/Concessions
A10: nr | B10: 4100106 Vacancy Loss | C10: -13725.89 | D10: -14532.17 | E10: -25005.29 | F10: -18833.49 | G10: -7135.31 | H10: -3387.5 | I10: -2806.89 | J10: -105.42 | K10: -1181.42 | L10: -2687.1 | M10: -3492.74 | N10: -2583 | O10: -95476.22
A11: nr | B11: 4100107 Concessions | C11: 0 | D11: 0 | E11: 0 | F11: 0 | G11: -99.86 | H11: 0 | I11: 0 | J11: 0 | K11: 0 | L11: 0 | M11: 0 | N11: 0 | O11: -99.86
A12: bd | B12: Bad Debt
A13: bd | B13: 4100112 Net Prepaids | C13: 732.09 | D13: 5.94 | E13: -2385.74 | F13: 789.69 | G13: 1159.41 | H13: -2248.45 | I13: 960.86 | J13: 64.26 | K13: -1337.56 | L13: -133.27 | M13: 865.34 | N13: -785.12 | O13: -2312.55
A14: bd | B14: 4100113 Net Delinquency | C14: -7210.84 | D14: -15776.46 | E14: -13010.57 | F14: 1307.36 | G14: -4534.37 | H14: 2586.83 | I14: -1844.19 | J14: -1177.15 | K14: 428.94 | L14: -1032.18 | M14: 66.59 | N14: -368.77 | O14: -40564.81
A15: rw | B15: RUBS - Water/Sewer
A16: rw | B16: 4101800 Water Reimbursement | C16: 0 | D16: 0 | E16: 0 | F16: 0 | G16: 2670 | H16: 4240 | I16: 4151 | J16: 0 | K16: 0 | L16: 0 | M16: 0 | N16: 0 | O16: 11061
A17: ro | B17: RUBS - Electric/Gas/Other
A18: rt | B18: 4101830 Trash Reimbursement | C18: 1148.04 | D18: 1127.42 | E18: 818.24 | F18: 919.17 | G18: 760.65 | H18: 705.83 | I18: 760 | J18: 0 | K18: 0 | L18: 0 | M18: 0 | N18: 0 | O18: 6239.35
A19: oi | B19: Other Income
A20: oi | B20: Other Income | C20: 0 | D20: 0 | E20: 0 | F20: 0 | G20: 0 | H20: 0 | I20: 0 | J20: 0 | K20: 0 | L20: 0 | M20: 0 | N20: 0 | O20: 0
A21: oi | B21: 4100200 Month to Month | C21: 0 | D21: 0 | E21: 0 | F21: 0 | G21: 135.89 | H21: 400 | I21: 0 | J21: 0 | K21: 0 | L21: 0 | M21: 0 | N21: 0 | O21: 535.89
A22: oi | B22: 4100600 Cleaning fee/Damage Fee | C22: 0 | D22: 0 | E22: 28.7 | F22: 0 | G22: 0 | H22: 0 | I22: 0 | J22: 0 | K22: 0 | L22: 0 | M22: 0 | N22: 0 | O22: 28.7
A23: oi | B23: 4100700 Carport Parking | C23: 105 | D23: 210 | E23: 105 | F23: 141.17 | G23: 210 | H23: 148.17 | I23: 210 | J23: 175 | K23: 140 | L23: 175 | M23: 175 | N23: 175 | O23: 1969.34
A24: oi | B24: 4100800 Pet Fee | C24: 180 | D24: 180 | E24: 135 | F24: 190 | G24: 145.2 | H24: 120 | I24: 120 | J24: 120 | K24: 145 | L24: 160 | M24: 160 | N24: 185 | O24: 1840.2
A25: oi | B25: 4100900 Deposit Forfeiture | C25: 0 | D25: 4500 | E25: 3499 | F25: 350 | G25: 0 | H25: 0 | I25: 0 | J25: 2440 | K25: 0 | L25: 0 | M25: 404.5 | N25: 718.22 | O25: 11911.72
A26: oi | B26: 4101100 Late Charges | C26: 582 | D26: 339.07 | E26: 64.77 | F26: 949.5 | G26: 410 | H26: 1474 | I26: 969 | J26: 1003.8 | K26: 863.5 | L26: 1166.4 | M26: 104.9 | N26: 629.5 | O26: 8556.44
A27: oi | B27: 4101200 NSF Charges | C27: 50 | D27: 0 | E27: 7 | F27: 93 | G27: 0 | H27: 0 | I27: 100 | J27: 200 | K27: 150 | L27: 50 | M27: 50 | N27: 0 | O27: 700
A28: oi | B28: 4101400 Application Fees | C28: 400 | D28: 390 | E28: 149 | F28: 1347 | G28: 660 | H28: 0 | I28: 75 | J28: 0 | K28: 0 | L28: 225 | M28: 375 | N28: 100 | O28: 3721
A29: oi | B29: 4101500 Washer/Dryer Income | C29: 376.07 | D29: 480 | E29: 318.23 | F29: 952.5 | G29: 1135.2 | H29: 1813.87 | I29: 1627.41 | J29: 1850.61 | K29: 1627.42 | L29: 1600.97 | M29: 1633.17 | N29: 1786.45 | O29: 15201.9
A30: oi | B30: 4101600 Administrative Fee | C30: 420 | D30: 0 | E30: 149 | F30: 637 | G30: 400 | H30: 0 | I30: 0 | J30: 110 | K30: 10 | L30: 110 | M30: 300 | N30: -95 | O30: 2041
A31: oi | B31: 4101835 Valet Trash Reimbursement | C31: 44.84 | D31: 125.97 | E31: 251.61 | F31: 619.77 | G31: 834.89 | H31: 1166.5 | I31: 1060.48 | J31: 0 | K31: 0 | L31: 0 | M31: 0 | N31: 0 | O31: 4104.06
... A36: rev | B36: Total Revenue | C36: 74884.47 | D36: 70655.25 | E36: 60080.61 | F36: 85315.94 | G36: 92114.84 | H36: 102675.02 | I36: 101054.77 | J36: 106890.72 | K36: 104771.09 | L36: 103805.77 | M36: 103488.1 | N36: 102709.24 | O36: 1108445.8
B38: Expense
A39: cs | B39: Contract Services
A40: cs | B40: 5500200 Equipment Rental and Expense | C40: 0 | D40: 0 | E40: 0 | F40: 0 | G40: 0 | H40: 0 | I40: 1604.27 | J40: 0 | K40: 0 | L40: 0 | M40: 0 | N40: 392 | O40: 1996.27
A41: cs | B41: 5500300 Landscaping | C41: 811.88 | D41: 811.88 | E41: 811.88 | F41: 811.88 | G41: 811.88 | H41: 811.88 | I41: 811.88 | J41: 811.88 | K41: 811.88 | L41: 811.88 | M41: 811.88 | N41: 811.88 | O41: 9742.56
A42: cs | B42: 5500350 Landscaping Seasonal | C42: 0 | D42: 0 | E42: 447.55 | F42: 0 | G42: 0 | H42: 0 | I42: 0 | J42: 0 | K42: 0 | L42: 0 | M42: 0 | N42: 0 | O42: 447.55
A43: cs | B43: 5500700 Pest Control | C43: 0 | D43: 0 | E43: 107.98 | F43: 0 | G43: 363.97 | H43: 107.98 | I43: 107.98 | J43: 118.78 | K43: 0 | L43: 237.56 | M43: 0 | N43: 237.56 | O43: 1281.81
A44: cs | B44: 5500800 Alarm Monitoring | C44: 0 | D44: 0 | E44: 0 | F44: 0 | G44: 0 | H44: 0 | I44: 584.56 | J44: 0 | K44: 681.99 | L44: 2432.06 | M44: 0 | N44: 1694.8 | O44: 5393.41
A45: cs | B45: 5500900 Washer/Dryer Expense | C45: 1203.2 | D45: 1203.2 | E45: 1203.21 | F45: 4690.54 | G45: 0 | H45: 2063.27 | I45: 0 | J45: 1806.42 | K45: 0 | L45: 1815.35 | M45: 3761.86 | N45: 0 | O45: 17747.05
A46: rm | B46: Repair & Maintenance
A47: rm | B47: 5700100 Carpentry | C47: 0 | D47: 21.62 | E47: 0 | F47: 0 | G47: 0 | H47: 0 | I47: 0 | J47: 0 | K47: 0 | L47: 0 | M47: 0 | N47: -32.12 | O47: -10.5
A48: rm | B48: 5700200 Paint Contract | C48: 1828.3 | D48: 5574.56 | E48: 1910 | F48: 3200.6 | G48: 9664.62 | H48: 2274.8 | I48: 0 | J48: 443.83 | K48: 33.53 | L48: 1010.8 | M48: 2716 | N48: 1377.4 | O48: 30034.44
A49: rm | B49: 5700500 Small Tools | C49: 0 | D49: 260.68 | E49: 0 | F49: 359.23 | G49: 23.71 | H49: 0 | I49: 0 | J49: 0 | K49: 0 | L49: 0 | M49: 0 | N49: 0 | O49: 643.62
A50: rm | B50: 5700700 Electrical Parts and Labor | C50: 63.36 | D50: 92.88 | E50: 0 | F50: 25.94 | G50: 154.66 | H50: 103.4 | I50: 0 | J50: 0 | K50: 94.77 | L50: 12.59 | M50: 0 | N50: 0 | O50: 547.6
A51: rm | B51: 5700900 Air Conditioning and Heat | C51: 0 | D51: 350.02 | E51: 0 | F51: 165.75 | G51: 1213.2 | H51: 283.9 | I51: 496.71 | J51: 583.31 | K51: 158.23 | L51: 1544.37 | M51: 51.96 | N51: 0 | O51: 4847.45
A52: rm | B52: 5701000 Pool Supplies and Repairs | C52: 0 | D52: 180.03 | E52: 0 | F52: 558.27 | G52: 538.9 | H52: 270.62 | I52: 299.13 | J52: 0 | K52: 15.99 | L52: 249.23 | M52: 0 | N52: 968.99 | O52: 3081.16
A53: rm | B53: 5701100 General Supplies | C53: 0 | D53: 0 | E53: 0 | F53: 0 | G53: 0 | H53: 0 | I53: 0 | J53: 0 | K53: 626.6 | L53: 0 | M53: 0 | N53: 0 | O53: 626.6
A54: rm | B54: 5701200 Landscaping Supplies | C54: 0 | D54: 0 | E54: 0 | F54: 351.38 | G54: 10.29 | H54: 0 | I54: 0 | J54: 0 | K54: 0 | L54: 0 | M54: 0 | N54: 0 | O54: 361.67
A55: rm | B55: 5701300 Plumbing Labor and Parts | C55: 72.53 | D55: 767.46 | E55: 0 | F55: 638.51 | G55: -57.85 | H55: 179.37 | I55: 0 | J55: 0 | K55: 240.17 | L55: 467.66 | M55: 45.45 | N55: 0 | O55: 2353.3
A56: rm | B56: 5701600 Glass and Mirror | C56: 0 | D56: 0 | E56: 0 | F56: 0 | G56: 0 | H56: 0 | I56: 0 | J56: 0 | K56: 708.36 | L56: 0 | M56: 0 | N56: 0 | O56: 708.36
A57: rm | B57: 5701700 Driveway and Sidewalk Repairs | C57: 0 | D57: 0 | E57: 0 | F57: 110.22 | G57: 0 | H57: 0 | I57: 0 | J57: 0 | K57: 0 | L57: 0 | M57: 0 | N57: 0 | O57: 110.22
A58: rm | B58: 5701800 Appliance | C58: 672.8 | D58: 483.61 | E58: 0 | F58: 402 | G58: 361.15 | H58: 78.18 | I58: 0 | J58: 0 | K58: 619.35 | L58: 416.09 | M58: 125.12 | N58: 419.02 | O58: 3577.32
... A66: rm | B66: 5709901 Vendor Rebate | C66: 0 | D66: 0 | E66: 0 | F66: 0 | G66: 0 | H66: -88.57 | I66: 0 | J66: 0 | K66: -830.06 | L66: 0 | M66: 0 | N66: -95.17 | O66: -1013.8
A67: ad | B67: Administrative
A68: ad | B68: 5400100 Office Supplies/General | C68: 10.8 | D68: 55.04 | E68: 263.47 | F68: 14.6 | G68: 638.36 | H68: 34.77 | I68: 16.9 | J68: 217.3 | K68: 9.46 | L68: 9.6 | M68: 315.18 | N68: 10 | O68: 1595.48
A69: ad | B69: 5400200 Postage | C69: 0 | D69: 34.12 | E69: 90.12 | F69: 8.76 | G69: 23.68 | H69: 56.94 | I69: 28.57 | J69: 21.5 | K69: 42.99 | L69: 25.07 | M69: 64.13 | N69: 60.83 | O69: 456.71
A70: ad | B70: 5400900 Auto and Travel | C70: 148.74 | D70: 0 | E70: 200 | F70: 385 | G70: 1027.6 | H70: 0 | I70: 0 | J70: 189 | K70: 0 | L70: 837.2 | M70: 249.98 | N70: 0 | O70: 3037.52
A71: ad | B71: 5401000 Dues and Subscription | C71: 55.36 | D71: 0 | E71: 0 | F71: 134.56 | G71: 0 | H71: 0 | I71: 0 | J71: 0 | K71: 0 | L71: 796.31 | M71: 1592.6 | N71: 0 | O71: 2578.83
A72: ad | B72: 5401200 Application Screening | C72: 93.36 | D72: 93.36 | E72: 93.36 | F72: 93.36 | G72: 93.36 | H72: 93.36 | I72: 0 | J72: 6.81 | K72: 0 | L72: 3.2 | M72: 30.44 | N72: 30.44 | O72: 631.05
A73: ad | B73: 5401300 Legal and Professional | C73: 0 | D73: 2482.98 | E73: 0 | F73: 0 | G73: 0 | H73: 0 | I73: 1696.25 | J73: 0 | K73: 0 | L73: 0 | M73: 0 | N73: 0 | O73: 4179.23
A74: ad | B74: 5401400 Evictions | C74: 200 | D74: 188.95 | E74: 0 | F74: 0 | G74: 0 | H74: 0 | I74: 154.22 | J74: 0 | K74: 0 | L74: 0 | M74: 0 | N74: 0 | O74: 543.17
A75: ad | B75: 5401700 Computer Fees/Permits | C75: 728.9 | D75: 27.76 | E75: 904.74 | F75: 872.29 | G75: 223.25 | H75: 101.27 | I75: 218.67 | J75: 2043.21 | K75: 190.01 | L75: 128.95 | M75: 721.66 | N75: 755.99 | O75: 6916.7
A76: ad | B76: 5401900 Bank Charges | C76: 164.7 | D76: 195.23 | E76: 184.09 | F76: 164.41 | G76: 234.88 | H76: 158.2 | I76: 130.54 | J76: 137.27 | K76: 186.47 | L76: 188.54 | M76: 142.34 | N76: 106.75 | O76: 1993.42
A77: ad | B77: 5402000 Employee Relations | C77: 26.52 | D77: 0 | E77: 230.17 | F77: 226.67 | G77: 0 | H77: 0 | I77: 475 | J77: 0 | K77: 0 | L77: 0 | M77: 0 | N77: 0 | O77: 958.36
A78: m | B78: Marketing
A79: m | B79: 5600200 Advertising Media | C79: 0 | D79: 0 | E79: 0 | F79: 1377.78 | G79: 908 | H79: 0 | I79: 0 | J79: 0 | K79: 1816 | L79: 0 | M79: 908 | N79: 454 | O79: 5463.78
A80: m | B80: 5600500 Mini Model | C80: 0 | D80: 0 | E80: 0 | F80: 141.25 | G80: 0 | H80: 0 | I80: 0 | J80: 0 | K80: 0 | L80: 0 | M80: 0 | N80: 0 | O80: 141.25
A81: m | B81: 5600900 Signs and Banners | C81: 0 | D81: 998.08 | E81: 0 | F81: 0 | G81: 0 | H81: 0 | I81: 0 | J81: 0 | K81: 0 | L81: 0 | M81: 0 | N81: 0 | O81: 998.08
A82: m | B82: 5610400 Resident Relations | C82: 0 | D82: 0 | E82: 127.55 | F82: 0 | G82: 138.5 | H82: 0 | I82: 0 | J82: 0 | K82: 250 | L82: 0 | M82: 0 | N82: 0 | O82: 516.05
A83: m | B83: 5610600 Marketing Materials | C83: 0 | D83: 473.05 | E83: 127.55 | F83: 0 | G83: 37.49 | H83: 0 | I83: 0 | J83: 0 | K83: 0 | L83: 0 | M83: 0 | N83: 0 | O83: 638.09
A84: pr | B84: Payroll
A85: pr | B85: 5100100 Managers and Assistants | C85: 1341.2 | D85: 1152.2 | E85: 4463.55 | F85: 3231.2 | G85: 3735.21 | H85: 3939.96 | I85: 3627.58 | J85: 5111.93 | K85: 3638.08 | L85: 4464.96 | M85: 3900.58 | N85: 2535.58 | O85: 41142.03
A86: pr | B86: 5100200 Leasing | C86: 0 | D86: 0 | E86: 0 | F86: 0 | G86: 0 | H86: 1277.72 | I86: 0 | J86: 0 | K86: 0 | L86: 0 | M86: 0 | N86: 0 | O86: 1277.72
A87: pr | B87: 5100600 General Maintenance Salaries | C87: 0 | D87: 769.45 | E87: 454.35 | F87: 1214.27 | G87: 214.5 | H87: 3322.8 | I87: 1238.45 | J87: 0 | K87: 390 | L87: 2930.13 | M87: 0 | N87: 1733.56 | O87: 12267.51
A88: pr | B88: 5100900 Incentives | C88: 0 | D88: 400 | E88: 0 | F88: 1800 | G88: 1100 | H88: 600 | I88: 300 | J88: 0 | K88: 480 | L88: 1080 | M88: 120 | N88: 135 | O88: 6015
A89: pr | B89: 5280000 Payroll Taxes | C89: 153.51 | D89: 178.7 | E89: 350.5 | F89: 423.56 | G89: 380.46 | H89: 341.75 | I89: 271.95 | J89: 666.79 | K89: 520.01 | L89: 435.68 | M89: 300.16 | N89: 200.95 | O89: 4224.02
A90: pr | B90: 5280100 Workers Compensation | C90: 23.36 | D90: 2.14 | E90: 2.48 | F90: 7.11 | G90: 27.14 | H90: 14.83 | I90: 7.24 | J90: 5.79 | K90: 4.76 | L90: 19.42 | M90: 18.13 | N90: 9.49 | O90: 141.89
A91: w | B91: Water/Sewer
A92: w | B92: 5800300 Water | C92: 6843.75 | D92: 5492.7 | E92: 5674.43 | F92: 5635.35 | G92: 6209.14 | H92: 5149.47 | I92: 5405.45 | J92: 5337.29 | K92: 5551.64 | L92: 5448.33 | M92: 5432.76 | N92: 5831.32 | O92: 68011.63
A93: tr | B93: Trash
A94: tr | B94: 5800400 Trash Removal | C94: 0 | D94: 1518 | E94: 2418 | F94: 1518 | G94: 2440.55 | H94: 1518 | I94: 1624.2 | J94: 1624.2 | K94: 2629.26 | L94: 1624.2 | M94: 1624 | N94: 1624.2 | O94: 20162.61
A95: tr | B95: 5800401 Valet Trash | C95: 856.6 | D95: 2550.79 | E95: 0 | F95: 772.55 | G95: 772.55 | H95: 918.53 | I95: 918.53 | J95: 263.47 | K95: 830.06 | L95: 200 | M95: 1080.06 | N95: 968.53 | O95: 10131.67
A96: e | B96: Electric
A97: e | B97: 5800100 Electricity | C97: 618.3 | D97: 552.71 | E97: 638.36 | F97: 347.37 | G97: 648.03 | H97: 582.23 | I97: 513.13 | J97: 648.6 | K97: 622.88 | L97: 522.52 | M97: 517.48 | N97: 673.93 | O97: 6885.54
A98: e | B98: 5800101 Electricity - Vacant | C98: 579.94 | D98: 830.21 | E98: 962.24 | F98: 1640.88 | G98: 866.55 | H98: 1067.5 | I98: 512.09 | J98: 196.11 | K98: -858.19 | L98: 422.7 | M98: 261.8 | N98: 241.75 | O98: 6723.58
A99: o | B99: Gas/Other
A100: o | B100: 5800500 Telephone | C100: 100.28 | D100: 73.87 | E100: 73.63 | F100: 59.92 | G100: 60.28 | H100: 480.09 | I100: 60.34 | J100: 60.34 | K100: 60.33 | L100: 60.33 | M100: 60.33 | N100: 280.79 | O100: 1430.53
A101: mf | B101: Management Fee
A102: mf | B102: 5900100 Management Fees | C102: 2995.38 | D102: 2826.21 | E102: 2403.22 | F102: 3412.64 | G102: 3684.59 | H102: 4107 | I102: 4022.19 | J102: 4275.63 | K102: 4190.84 | L102: 4152.23 | M102: 4019.53 | N102: 4028.37 | O102: 44117.83
A103: i | B103: Insurance
A104: i | B104: 6300100 Insurance | C104: 0 | D104: 0 | E104: 0 | F104: 0 | G104: 0 | H104: 0 | I104: 0 | J104: 3346.78 | K104: 3346.78 | L104: 3346.78 | M104: 3346.78 | N104: 3346.78 | O104: 16733.9
A105: tx | B105: Real Estate Taxes
A106: tx | B106: 6200100 Property Taxes | C106: 7867.13 | D106: 7867.13 | E106: 7867.13 | F106: 7867.13 | G106: 7867.13 | H106: 7867.13 | I106: 21857.1 | J106: 9033 | K106: 9033 | L106: 9033 | M106: 9033 | N106: 9033 | O106: 114224.88
A107: exp | B107: Total Expense | C107: 28395.29 | D107: 40113.74 | E107: 33884.98 | F107: 44985.02 | G107: 45515.57 | H107: 42881.02 | I107: 47566.48 | J107: 36949.24 | K107: 36669.87 | L107: 44844.48 | M107: 42761.07 | N107: 38450.38 | O107: 483017.14
A109: noi | B109: Net Operating Income | C109: 46489.18 | D109: 30541.51 | E109: 26195.63 | F109: 40330.92 | G109: 46599.27 | H109: 59794 | I109: 53488.29 | J109: 69941.48 | K109: 68101.22 | L109: 58961.29 | M109: 60727.03 | N109: 64258.86 | O109: 625428.68

Sheet nullvalues
A1: code | B1: category | C1: date1 | D1: date2 | E1: date3 | F1: date4 | G1: date5 | H1: date6 | I1: date7 | J1: date8 | K1: date9 | L1: date10 | M1: date11 | N1: date12 | O1: total

Sheet Sheet3
A1: code | B1: category | C1: date1 | D1: date2 | E1: date3 | F1: date4 | G1: date5 | H1: date6 | I1: date7 | J1: date8 | K1: date9 | L1: date10 | M1: date11 | N1: date12 | O1: total
